{
  "recordId": "cuhk-global-political-economy-mssc-2026-main-application-period",
  "universityId": "the-chinese-university-of-hong-kong",
  "sourceUrl": "https://www.gs.cuhk.edu.hk/admissions/application-deadline",
  "finalUrl": "https://www.gs.cuhk.edu.hk/admissions/application-deadline",
  "capturedAt": "2026-07-05T17:18:31.349328+00:00",
  "contentHash": "385cb5a0be2f7c5782e446d4b1dfe072dba56d0d42ceef2d86baf1fd339f34b3",
  "contentType": "text/html; charset=UTF-8",
  "bytesRead": 301078,
  "truncated": false,
  "excerpt": "The official programme page for MSSc in Global Political Economy lists Main application period opening on 2025-09-01 and closing on 2026-01-31. Source: https://www.gs.cuhk.edu.hk/admissions/application-deadline 31 January 2026",
  "excerptHash": "1daf7fbfbc9993253386a6676191fd62e0423a29aadd89d3344a80528640b02f",
  "contentSelector": "main",
  "matchedTextBefore": "",
  "matchedText": "The official programme page for MSSc in Global Political Economy lists Main application period opening on 2025-09-01 and closing on 2026-01-31. Source: https://www.gs.cuhk.edu.hk/admissions/application-deadline 31 January 2026",
  "matchedTextAfter": "*Excluding the Postgraduate Certificate in Laws programme offered by the Faculty of Law"
}
