{
  "recordId": "imperial-applied-biosciences-and-biotechnology-msc-2026-round-3",
  "universityId": "imperial-college-london",
  "sourceUrl": "https://www.imperial.ac.uk/study/courses/postgraduate-taught/2026/biosciences-biotechnology/",
  "finalUrl": "https://www.imperial.ac.uk/study/courses/postgraduate-taught/biosciences-biotechnology/",
  "capturedAt": "2026-07-05T17:17:34.580291+00:00",
  "contentHash": "34dc564bf669b1936f9d8f823008e50d3508d0ad8710ab43f31e063b006a84f4",
  "contentType": "text/html; charset=UTF-8",
  "bytesRead": 117003,
  "truncated": false,
  "excerpt": "Applications are now closed for 2026 entry.\nApplications are now closed for 2026 entry.\nApply by 23.59 (UK time) on the closing date of an application round, to ensure you receive a response on your application by the relevant decision date.\nApplications open on Monday 29 September 2025\nApplications close on Wednesday 7 January 2026\nApplications open on Thursday 8 January 2026\nApplications close on Wednesday 11 March 2026\nApplications open on Thursday 12 March 2026\nApplications close on Wednesday 29 April 2026",
  "excerptHash": "cdfb30a3a0a7aead2ba191aaf56fb39079713b4f042584f0a7535126104d94bd",
  "contentSelector": "main",
  "matchedTextBefore": "Gain an in-depth understanding of modern bioscience research and acquire the skills needed to pursue a career in the field.",
  "matchedText": "Applications are now closed for 2026 entry.",
  "matchedTextAfter": "Request info"
}
