{
  "recordId": "polyu-building-services-engineering-msc-2027-early-round",
  "universityId": "the-hong-kong-polytechnic-university",
  "sourceUrl": "https://www.polyu.edu.hk/study/pg/tpg/2027/33084-bem-bsm",
  "finalUrl": "https://www.polyu.edu.hk/study/pg/tpg/2027/33084-bem-bsm",
  "capturedAt": "2026-07-05T17:18:39.433883+00:00",
  "contentHash": "611d702b6bf182a833c469aec555a94f36ca2fff578166db8e08296adf5981d2",
  "contentType": "text/html; charset=UTF-8",
  "bytesRead": 83177,
  "truncated": false,
  "excerpt": "The official programme page for MSc in Building Services Engineering lists Early round opening on 2026-07-02 and closing on 2026-10-20. Source: https://www.polyu.edu.hk/study/pg/tpg/2027/33084-bem-bsm Local Application Deadline: 20 Oct 2026 (Early Round) Non-Local Application Deadline: 20 Oct 2026 (Early Round)",
  "excerptHash": "d3bff9b5d4466f25c5f7f76d05afa2a83277f185e89d004da68ffc30ae9f6142",
  "contentSelector": "main",
  "matchedTextBefore": "for details.",
  "matchedText": "The official programme page for MSc in Building Services Engineering lists Early round opening on 2026-07-02 and closing on 2026-10-20. Source: https://www.polyu.edu.hk/study/pg/tpg/2027/33084-bem-bsm Local Application Deadline: 20 Oct 2026 (Early Round) Non-Local Application Deadline: 20 Oct 2026 (Early Round)",
  "matchedTextAfter": "Local - Mixed Mode"
}
