{
  "universities": {
    "princeton-university": {
      "sourceUrl": "https://gradschool.princeton.edu/academics/degrees-requirements/fields-study",
      "checkedAt": "2026-07-24T07:01:29.882280+00:00",
      "itemCount": 12,
      "applicationOpensAt": null,
      "catalogHash": "5d880a24d06d0abbb2b29d21f3aede03017d7e8c5bb0e0a6d0c747bde1e7cff6",
      "programmes": {
        "princeton-architecture-march": {
          "name": "M.Arch. in Architecture",
          "degreeType": "MARCH",
          "faculty": "Princeton University Graduate School",
          "department": "Architecture",
          "parseStatus": "incomplete",
          "deadlineHash": "5953bf999c6a4041d1ccdc01cc96aeb7c73a5bc7726c1c231a527a27017bc907"
        },
        "princeton-chemical-and-biological-engineering-meng": {
          "name": "M.Eng. in Chemical and Biological Engineering",
          "degreeType": "MENG",
          "faculty": "Princeton University Graduate School",
          "department": "Chemical and Biological Engineering",
          "parseStatus": "incomplete",
          "deadlineHash": "f2793e7fdbca2f5df72f9d99f79b285331fd5e40a4b7d6a34a948c980a5b2fc8"
        },
        "princeton-chemical-and-biological-engineering-mse": {
          "name": "M.S.E. in Chemical and Biological Engineering",
          "degreeType": "MSE",
          "faculty": "Princeton University Graduate School",
          "department": "Chemical and Biological Engineering",
          "parseStatus": "incomplete",
          "deadlineHash": "f2793e7fdbca2f5df72f9d99f79b285331fd5e40a4b7d6a34a948c980a5b2fc8"
        },
        "princeton-civil-and-environmental-engineering-meng": {
          "name": "M.Eng. in Civil and Environmental Engineering",
          "degreeType": "MENG",
          "faculty": "Princeton University Graduate School",
          "department": "Civil and Environmental Engineering",
          "parseStatus": "incomplete",
          "deadlineHash": "bdb99f075579d643869951113b630d56c30982f77241dc2cf69e05f67e2a2205"
        },
        "princeton-civil-and-environmental-engineering-mse": {
          "name": "M.S.E. in Civil and Environmental Engineering",
          "degreeType": "MSE",
          "faculty": "Princeton University Graduate School",
          "department": "Civil and Environmental Engineering",
          "parseStatus": "incomplete",
          "deadlineHash": "bdb99f075579d643869951113b630d56c30982f77241dc2cf69e05f67e2a2205"
        },
        "princeton-computer-science-mse": {
          "name": "MSE in Computer Science",
          "degreeType": "MSE",
          "faculty": "Princeton University Graduate School",
          "department": "Computer Science",
          "parseStatus": "incomplete",
          "deadlineHash": "b61eea9d7d961fdf452a53ef53cfab27fc686c7782776fa9e1f96cd99212d41a"
        },
        "princeton-electrical-and-computer-engineering-meng": {
          "name": "M.Eng. in Electrical and Computer Engineering",
          "degreeType": "MENG",
          "faculty": "Princeton University Graduate School",
          "department": "Electrical and Computer Engineering",
          "parseStatus": "incomplete",
          "deadlineHash": "facb8e2e5fefe693520c04406dc33845f12d15fe339d4018841a0c8e44a22692"
        },
        "princeton-finance-mfin": {
          "name": "M.Fin. in Finance",
          "degreeType": "MFIN",
          "faculty": "Princeton University Graduate School",
          "department": "Finance",
          "parseStatus": "incomplete",
          "deadlineHash": "3922ce759d3159ca5bb89e26d9757d4f1d89724f77af87c30afaa13d239d611a"
        },
        "princeton-mechanical-and-aerospace-engineering-meng": {
          "name": "M.Eng. in Mechanical and Aerospace Engineering",
          "degreeType": "MENG",
          "faculty": "Princeton University Graduate School",
          "department": "Mechanical and Aerospace Engineering",
          "parseStatus": "incomplete",
          "deadlineHash": "251d67aa604cf5d3facafab9f2fc92de9d5b4bab309e165f148abf1c5aa230b0"
        },
        "princeton-mechanical-and-aerospace-engineering-mse": {
          "name": "M.S.E. in Mechanical and Aerospace Engineering",
          "degreeType": "MSE",
          "faculty": "Princeton University Graduate School",
          "department": "Mechanical and Aerospace Engineering",
          "parseStatus": "incomplete",
          "deadlineHash": "251d67aa604cf5d3facafab9f2fc92de9d5b4bab309e165f148abf1c5aa230b0"
        },
        "princeton-school-of-public-and-international-affairs-mpa": {
          "name": "M.P.A. in Princeton School of Public and International Affairs",
          "degreeType": "MPA",
          "faculty": "Princeton University Graduate School",
          "department": "Princeton School of Public and International Affairs",
          "parseStatus": "incomplete",
          "deadlineHash": "3ec082baeb9b51612ae47d4181db67ed1e1ac730edb9d3c33776b01e741c5774"
        },
        "princeton-school-of-public-and-international-affairs-mpp": {
          "name": "M.P.P. in Princeton School of Public and International Affairs",
          "degreeType": "MPP",
          "faculty": "Princeton University Graduate School",
          "department": "Princeton School of Public and International Affairs",
          "parseStatus": "incomplete",
          "deadlineHash": "3ec082baeb9b51612ae47d4181db67ed1e1ac730edb9d3c33776b01e741c5774"
        }
      }
    }
  }
}
