{
  "universities": {
    "the-hong-kong-university-of-science-and-technology": {
      "sourceUrl": "https://prog-crs.hkust.edu.hk/pgprog/print_result.php?is_s=Y&degree%5B%5D=MSC&degree%5B%5D=MA&degree%5B%5D=MPM&degree%5B%5D=MPP&year=2026-27",
      "checkedAt": "2026-07-23T10:17:29.428610+00:00",
      "itemCount": 48,
      "applicationOpensAt": "2025-09-01",
      "catalogHash": "2a540fb1907e333f014272d2b2016c93238aef1e67d642ff118e9849b74bc060",
      "programmes": {
        "hkust-arts-and-machine-creativity-ma": {
          "name": "Master of Arts in Arts and Machine Creativity",
          "degreeType": "MA",
          "faculty": "Division of Arts and Machine Creativity, Academy of Interdisciplinary Studies",
          "department": "Division of Arts and Machine Creativity, Academy of Interdisciplinary Studies",
          "parseStatus": "parsed",
          "deadlineHash": "f0196720e0fd41c9a1b29bd11a5a8bbf0712612a761ff93b4bed6aacd6adb6c2"
        },
        "hkust-chinese-culture-ma": {
          "name": "Master of Arts in Chinese Culture",
          "degreeType": "MA",
          "faculty": "Division of Humanities",
          "department": "Division of Humanities",
          "parseStatus": "parsed",
          "deadlineHash": "d63503c2c0033b979d16994b3c72e9f2481c16846a886e083d3e45746f55b403"
        },
        "hkust-international-language-education-ma": {
          "name": "Master of Arts in International Language Education",
          "degreeType": "MA",
          "faculty": "School of Humanities and Social Science",
          "department": "School of Humanities and Social Science",
          "parseStatus": "parsed",
          "deadlineHash": "2375d2e908ea65d5428bdb68d6bc6b32d5e335ce7c0bef324c8e575c608f01c6"
        },
        "hkust-master-of-public-management-mpm": {
          "name": "Master of Public Management",
          "degreeType": "MPM",
          "faculty": "Division of Public Policy",
          "department": "Division of Public Policy",
          "parseStatus": "parsed",
          "deadlineHash": "600a662eabd2df79326f7eeba66ea7f520c607d31036eca1fd9b6ffc010cb2a7"
        },
        "hkust-master-of-public-policy-mpp": {
          "name": "Master of Public Policy",
          "degreeType": "MPP",
          "faculty": "Division of Public Policy",
          "department": "Division of Public Policy",
          "parseStatus": "parsed",
          "deadlineHash": "600a662eabd2df79326f7eeba66ea7f520c607d31036eca1fd9b6ffc010cb2a7"
        },
        "hkust-accounting-msc": {
          "name": "Master of Science in Accounting",
          "degreeType": "MSc",
          "faculty": "Department of Accounting",
          "department": "Department of Accounting",
          "parseStatus": "parsed",
          "deadlineHash": "b2036895609602612245c4aa1944f0528816f4569c088d7033615aa7eeaf72d4"
        },
        "hkust-aeronautical-engineering-msc": {
          "name": "Master of Science in Aeronautical Engineering",
          "degreeType": "MSc",
          "faculty": "Department of Mechanical and Aerospace Engineering",
          "department": "Department of Mechanical and Aerospace Engineering",
          "parseStatus": "parsed",
          "deadlineHash": "00e9b571fb50623808a5688270fefe8e4e714de84679cde9d6e817f6720b19d0"
        },
        "hkust-artificial-intelligence-msc": {
          "name": "Master of Science in Artificial Intelligence",
          "degreeType": "MSc",
          "faculty": "Department of Computer Science and Engineering",
          "department": "Department of Computer Science and Engineering",
          "parseStatus": "parsed",
          "deadlineHash": "193e46cbc2970197c7a90fff69f77ac309966138f7194cd26987be857d40846b"
        },
        "hkust-ai-and-entrepreneurship-msc": {
          "name": "Master of Science in AI and Entrepreneurship",
          "degreeType": "MSc",
          "faculty": "Department of Computer Science and Engineering",
          "department": "Department of Computer Science and Engineering",
          "parseStatus": "parsed",
          "deadlineHash": "193e46cbc2970197c7a90fff69f77ac309966138f7194cd26987be857d40846b"
        },
        "hkust-analytical-chemistry-msc": {
          "name": "Master of Science in Analytical Chemistry",
          "degreeType": "MSc",
          "faculty": "Department of Chemistry",
          "department": "Department of Chemistry",
          "parseStatus": "parsed",
          "deadlineHash": "d25600ec044750ac400b520105f7097c7e2ed8e0aee7747f9314201e5827927d"
        },
        "hkust-business-analytics-msc": {
          "name": "Master of Science in Business Analytics",
          "degreeType": "MSc",
          "faculty": "Department of Information Systems, Business Statistics and Operations Management",
          "department": "Department of Information Systems, Business Statistics and Operations Management",
          "parseStatus": "parsed",
          "deadlineHash": "45b0d6bb0dc456a60e37935f694d4a16d7cc1f697e0a891a940d352e3f5d8d09"
        },
        "hkust-big-data-technology-msc": {
          "name": "Master of Science in Big Data Technology",
          "degreeType": "MSc",
          "faculty": "Department of Computer Science and Engineering , School of Engineering Department of Mathematics , School of Science",
          "department": "Department of Computer Science and Engineering , School of Engineering Department of Mathematics , School of Science",
          "parseStatus": "parsed",
          "deadlineHash": "e367524a56650d77e217112adef61df4f33152eaba04bbe77bb1c6b0012efb67"
        },
        "hkust-biomolecular-engineering-and-health-informatics-msc": {
          "name": "Master of Science in Biomolecular Engineering and Health Informatics",
          "degreeType": "MSc",
          "faculty": "Department of Chemical and Biological Engineering",
          "department": "Department of Chemical and Biological Engineering",
          "parseStatus": "parsed",
          "deadlineHash": "981492307e8103c42a7e47c818f28d8511bcbf03e346230b6879f2d798be5d3d"
        },
        "hkust-biotechnology-msc": {
          "name": "Master of Science in Biotechnology",
          "degreeType": "MSc",
          "faculty": "Division of Life Science",
          "department": "Division of Life Science",
          "parseStatus": "parsed",
          "deadlineHash": "d25600ec044750ac400b520105f7097c7e2ed8e0aee7747f9314201e5827927d"
        },
        "hkust-chemical-and-energy-engineering-msc": {
          "name": "Master of Science in Chemical and Energy Engineering",
          "degreeType": "MSc",
          "faculty": "Department of Chemical and Biological Engineering",
          "department": "Department of Chemical and Biological Engineering",
          "parseStatus": "parsed",
          "deadlineHash": "981492307e8103c42a7e47c818f28d8511bcbf03e346230b6879f2d798be5d3d"
        },
        "hkust-data-driven-modeling-msc": {
          "name": "Master of Science in Data-Driven Modeling",
          "degreeType": "MSc",
          "faculty": "Department of Physics",
          "department": "Department of Physics",
          "parseStatus": "parsed",
          "deadlineHash": "7d31ddec51ef6a211f9a12d67ecd880ead518c4b34c1b7dcca089f201bb658f0"
        },
        "hkust-drug-regulatory-affairs-and-policy-msc": {
          "name": "Master of Science in Drug Regulatory Affairs and Policy",
          "degreeType": "MSc",
          "faculty": "Division of Life Science",
          "department": "Division of Life Science",
          "parseStatus": "parsed",
          "deadlineHash": "0a703694811a03b26f3bc8af82abf7cc9cc72b033d8c716e3a39b2df91cc9345"
        },
        "hkust-economics-msc": {
          "name": "Master of Science in Economics",
          "degreeType": "MSc",
          "faculty": "Department of Economics",
          "department": "Department of Economics",
          "parseStatus": "parsed",
          "deadlineHash": "5edd4a31fb1d5042a8e833b20f3aa2f201285730243530e900278126c2533e61"
        },
        "hkust-engineering-enterprise-management-msc": {
          "name": "Master of Science in Engineering Enterprise Management",
          "degreeType": "MSc",
          "faculty": "Department of Industrial Engineering and Decision Analytics",
          "department": "Department of Industrial Engineering and Decision Analytics",
          "parseStatus": "parsed",
          "deadlineHash": "99b6146b7386ffc36b19588d5e9666a25c28bc6a4db630447279e92e89cd6f75"
        },
        "hkust-environmental-health-and-safety-msc": {
          "name": "Master of Science in Environmental Health and Safety",
          "degreeType": "MSc",
          "faculty": "Department of Ocean Science",
          "department": "Department of Ocean Science",
          "parseStatus": "parsed",
          "deadlineHash": "d25600ec044750ac400b520105f7097c7e2ed8e0aee7747f9314201e5827927d"
        },
        "hkust-entrepreneurial-leadership-in-biotechnology-msc": {
          "name": "Master of Science in Entrepreneurial Leadership in Biotechnology",
          "degreeType": "MSc",
          "faculty": "Division of Life Science",
          "department": "Division of Life Science",
          "parseStatus": "parsed",
          "deadlineHash": "d25600ec044750ac400b520105f7097c7e2ed8e0aee7747f9314201e5827927d"
        },
        "hkust-electronic-engineering-msc": {
          "name": "Master of Science in Electronic Engineering",
          "degreeType": "MSc",
          "faculty": "Department of Electronic and Computer Engineering",
          "department": "Department of Electronic and Computer Engineering",
          "parseStatus": "parsed",
          "deadlineHash": "ccc9a56c54774d991a082faa4331e6e2d92078e45416a2142967e8c8e74f620f"
        },
        "hkust-environmental-science-management-and-sustainability-msc": {
          "name": "Master of Science in Environmental Science, Management and Sustainability",
          "degreeType": "MSc",
          "faculty": "Division of Environment and Sustainability",
          "department": "Division of Environment and Sustainability",
          "parseStatus": "parsed",
          "deadlineHash": "d25600ec044750ac400b520105f7097c7e2ed8e0aee7747f9314201e5827927d"
        },
        "hkust-finance-msc": {
          "name": "Master of Science in Finance",
          "degreeType": "MSc",
          "faculty": "Department of Finance",
          "department": "Department of Finance",
          "parseStatus": "parsed",
          "deadlineHash": "08d8ae85d022dfe4955f9cefc46b45dcf6494a83e5dc34880ce2fdf2612799cf"
        },
        "hkust-financial-technology-msc": {
          "name": "Master of Science in Financial Technology",
          "degreeType": "MSc",
          "faculty": "School of Engineering , School of Business and Management and School of Science",
          "department": "School of Engineering , School of Business and Management and School of Science",
          "parseStatus": "parsed",
          "deadlineHash": "e367524a56650d77e217112adef61df4f33152eaba04bbe77bb1c6b0012efb67"
        },
        "hkust-family-office-and-family-business-msc": {
          "name": "Master of Science in Family Office and Family Business",
          "degreeType": "MSc",
          "faculty": "Department of Management",
          "department": "Department of Management",
          "parseStatus": "parsed",
          "deadlineHash": "45b0d6bb0dc456a60e37935f694d4a16d7cc1f697e0a891a940d352e3f5d8d09"
        },
        "hkust-global-china-studies-msc": {
          "name": "Master of Science in Global China Studies",
          "degreeType": "MSc",
          "faculty": "School of Humanities and Social Science",
          "department": "School of Humanities and Social Science",
          "parseStatus": "parsed",
          "deadlineHash": "f0196720e0fd41c9a1b29bd11a5a8bbf0712612a761ff93b4bed6aacd6adb6c2"
        },
        "hkust-global-finance-joint-degree-by-new-york-university-and-hkust-msc": {
          "name": "Master of Science in Global Finance (Joint Degree by New York University and HKUST)",
          "degreeType": "MSc",
          "faculty": "School of Business and Management",
          "department": "School of Business and Management",
          "parseStatus": "no-deadline",
          "deadlineHash": "4f53cda18c2baa0c0354bb5f9a3ecbe5ed12ab4d8e11ba873c2f11161202b945"
        },
        "hkust-global-marine-resources-management-dual-degrees-by-hkust-and-university-of-southampton-msc": {
          "name": "Master of Science in Global Marine Resources Management (Dual degrees by HKUST and University of Southampton)",
          "degreeType": "MSc",
          "faculty": "Department of Ocean Science",
          "department": "Department of Ocean Science",
          "parseStatus": "parsed",
          "deadlineHash": "d25600ec044750ac400b520105f7097c7e2ed8e0aee7747f9314201e5827927d"
        },
        "hkust-global-operations-msc": {
          "name": "Master of Science in Global Operations",
          "degreeType": "MSc",
          "faculty": "Department of Information Systems, Business Statistics and Operation Management",
          "department": "Department of Information Systems, Business Statistics and Operation Management",
          "parseStatus": "parsed",
          "deadlineHash": "76420e35f818e38cd5754cd073a636ff451eb7ab421ce75abecfa224735d2b7e"
        },
        "hkust-intelligent-building-technology-and-management-msc": {
          "name": "Master of Science in Intelligent Building Technology and Management",
          "degreeType": "MSc",
          "faculty": "Department of Mechanical and Aerospace Engineering",
          "department": "Department of Mechanical and Aerospace Engineering",
          "parseStatus": "parsed",
          "deadlineHash": "00e9b571fb50623808a5688270fefe8e4e714de84679cde9d6e817f6720b19d0"
        },
        "hkust-integrated-circuits-msc": {
          "name": "Master of Science in Integrated Circuits",
          "degreeType": "MSc",
          "faculty": "Department of Electronic and Computer Engineering",
          "department": "Department of Electronic and Computer Engineering",
          "parseStatus": "parsed",
          "deadlineHash": "ccc9a56c54774d991a082faa4331e6e2d92078e45416a2142967e8c8e74f620f"
        },
        "hkust-information-and-cyber-security-management-msc": {
          "name": "Master of Science in Information and Cyber Security Management",
          "degreeType": "MSc",
          "faculty": "Department of Information Systems, Business Statistics and Operations Management",
          "department": "Department of Information Systems, Business Statistics and Operations Management",
          "parseStatus": "parsed",
          "deadlineHash": "45b0d6bb0dc456a60e37935f694d4a16d7cc1f697e0a891a940d352e3f5d8d09"
        },
        "hkust-international-management-msc": {
          "name": "Master of Science in International Management",
          "degreeType": "MSc",
          "faculty": "School of Business and Management",
          "department": "School of Business and Management",
          "parseStatus": "parsed",
          "deadlineHash": "76420e35f818e38cd5754cd073a636ff451eb7ab421ce75abecfa224735d2b7e"
        },
        "hkust-information-systems-management-msc": {
          "name": "Master of Science in Information Systems Management",
          "degreeType": "MSc",
          "faculty": "Department of Information Systems, Business Statistics and Operations Management",
          "department": "Department of Information Systems, Business Statistics and Operations Management",
          "parseStatus": "parsed",
          "deadlineHash": "45b0d6bb0dc456a60e37935f694d4a16d7cc1f697e0a891a940d352e3f5d8d09"
        },
        "hkust-information-technology-msc": {
          "name": "Master of Science in Information Technology",
          "degreeType": "MSc",
          "faculty": "Department of Computer Science and Engineering",
          "department": "Department of Computer Science and Engineering",
          "parseStatus": "parsed",
          "deadlineHash": "193e46cbc2970197c7a90fff69f77ac309966138f7194cd26987be857d40846b"
        },
        "hkust-mathematics-for-educators-msc": {
          "name": "Master of Science in Mathematics for Educators",
          "degreeType": "MSc",
          "faculty": "Department of Mathematics",
          "department": "Department of Mathematics",
          "parseStatus": "parsed",
          "deadlineHash": "d25600ec044750ac400b520105f7097c7e2ed8e0aee7747f9314201e5827927d"
        },
        "hkust-financial-mathematics-msc": {
          "name": "Master of Science in Financial Mathematics",
          "degreeType": "MSc",
          "faculty": "Department of Mathematics",
          "department": "Department of Mathematics",
          "parseStatus": "parsed",
          "deadlineHash": "f73d29ffac9b9bb1dcaaddbd595213aaea74c213290f2e3c1ee4cb44a493b1bb"
        },
        "hkust-marketing-msc": {
          "name": "Master of Science in Marketing",
          "degreeType": "MSc",
          "faculty": "Department of Marketing",
          "department": "Department of Marketing",
          "parseStatus": "parsed",
          "deadlineHash": "76420e35f818e38cd5754cd073a636ff451eb7ab421ce75abecfa224735d2b7e"
        },
        "hkust-materials-engineering-msc": {
          "name": "Master of Science in Materials Engineering",
          "degreeType": "MSc",
          "faculty": "Department of Chemical and Biological Engineering",
          "department": "Department of Chemical and Biological Engineering",
          "parseStatus": "parsed",
          "deadlineHash": "56a53c55db29c5f13d254bdb9631af27d5a10a3d2f0b37a1bd84b16f8cec3f31"
        },
        "hkust-mechanical-engineering-msc": {
          "name": "Master of Science in Mechanical Engineering",
          "degreeType": "MSc",
          "faculty": "Department of Mechanical and Aerospace Engineering",
          "department": "Department of Mechanical and Aerospace Engineering",
          "parseStatus": "parsed",
          "deadlineHash": "43a1af2f8980e0cddaf7aa0ec0c76903eaeb4e2b8e350c8c09db3f4635775ae5"
        },
        "hkust-digital-and-sustainable-cities-master-of-engineering-in-digital-and-sustainable-cities-msc": {
          "name": "Master of Science in Digital and Sustainable Cities Master of Engineering in Digital and Sustainable Cities",
          "degreeType": "MSc",
          "faculty": "Department of Civil and Environmental Engineering",
          "department": "Department of Civil and Environmental Engineering",
          "parseStatus": "parsed",
          "deadlineHash": "83dd6721a8b321507bdf3dfbc8925ca041f48e7126f211e87f67e995920c41be"
        },
        "hkust-physics-msc": {
          "name": "Master of Science in Physics",
          "degreeType": "MSc",
          "faculty": "Department of Physics",
          "department": "Department of Physics",
          "parseStatus": "parsed",
          "deadlineHash": "0a703694811a03b26f3bc8af82abf7cc9cc72b033d8c716e3a39b2df91cc9345"
        },
        "hkust-telecommunications-msc": {
          "name": "Master of Science in Telecommunications",
          "degreeType": "MSc",
          "faculty": "Department of Electronic and Computer Engineering",
          "department": "Department of Electronic and Computer Engineering",
          "parseStatus": "parsed",
          "deadlineHash": "ccc9a56c54774d991a082faa4331e6e2d92078e45416a2142967e8c8e74f620f"
        },
        "hkust-technology-leadership-and-entrepreneurship-msc": {
          "name": "Master of Science in Technology Leadership and Entrepreneurship",
          "degreeType": "MSc",
          "faculty": "Division of Integrative Systems and Design , Academy of Interdisciplinary Studies School of Business and Management",
          "department": "Division of Integrative Systems and Design , Academy of Interdisciplinary Studies School of Business and Management",
          "parseStatus": "parsed",
          "deadlineHash": "f73d29ffac9b9bb1dcaaddbd595213aaea74c213290f2e3c1ee4cb44a493b1bb"
        },
        "hkust-pgd-ma-sosc": {
          "name": "Postgraduate Diploma in Social Science Master of Arts in Social Science",
          "degreeType": "MA",
          "faculty": "Division of Social Science",
          "department": "Division of Social Science",
          "parseStatus": "parsed",
          "deadlineHash": "45b6339beca2f316abff4730c64250400feacc941ed426e27688339b65d6af50"
        },
        "hkust-pgd-msc-ciem": {
          "name": "Postgraduate Diploma in Civil Infrastructural Engineering and Management Master of Science in Civil Infrastructural Engineering and Management",
          "degreeType": "MSc",
          "faculty": "Department of Civil and Environmental Engineering",
          "department": "Department of Civil and Environmental Engineering",
          "parseStatus": "parsed",
          "deadlineHash": "83dd6721a8b321507bdf3dfbc8925ca041f48e7126f211e87f67e995920c41be"
        },
        "hkust-pgd-msc-evem": {
          "name": "Postgraduate Diploma in Environmental Engineering and Management Master of Science in Environmental Engineering and Management",
          "degreeType": "MSc",
          "faculty": "Department of Civil and Environmental Engineering",
          "department": "Department of Civil and Environmental Engineering",
          "parseStatus": "parsed",
          "deadlineHash": "83dd6721a8b321507bdf3dfbc8925ca041f48e7126f211e87f67e995920c41be"
        }
      }
    }
  }
}
