{
  "items": [
    {
      "id": "new-programme:eth-agricultural-sciences-msc",
      "type": "new-programme",
      "status": "approved",
      "universityId": "eth-zurich-swiss-federal-institute-of-technology",
      "detectedAt": "2026-07-08T06:36:09.250065+00:00",
      "sourceUrl": "https://ethz.ch/content/dam/ethz/common/docs/master-profile/englisch/systemorientierte-wissenschaften/MSc-Agricultural-Sciences-Appendix.pdf",
      "programme": {
        "id": "eth-agricultural-sciences-msc",
        "universityId": "eth-zurich-swiss-federal-institute-of-technology",
        "name": "MSc Agricultural Sciences",
        "degreeType": "MSc",
        "faculty": "System-oriented Natural Sciences | Agricultural Sciences",
        "applicationUrl": "https://ethz.ch/en/studies/master/application.html",
        "sourceUrl": "https://ethz.ch/content/dam/ethz/common/docs/master-profile/englisch/systemorientierte-wissenschaften/MSc-Agricultural-Sciences-Appendix.pdf"
      },
      "windows": [
        {
          "intake": "Autumn 2026",
          "round": "International Bachelor's window",
          "applicantCategories": [
            "international-bachelors",
            "esop",
            "direct-doctorate"
          ],
          "opensAt": "2025-11-01",
          "opensAtBasis": "official",
          "closesAt": "2025-11-30"
        },
        {
          "intake": "Autumn 2026",
          "round": "Swiss Bachelor's window",
          "applicantCategories": [
            "swiss-bachelors"
          ],
          "opensAt": "2026-04-01",
          "opensAtBasis": "official",
          "closesAt": "2026-04-30"
        }
      ],
      "parseStatus": "parsed",
      "reviewReason": "Review the automatically discovered programme and application rounds.",
      "evidenceExcerpt": "ETH Zurich lists Agricultural Sciences MSc in its official profiles of requirements. The official application dates page lists Autumn 2026 master's application windows: International Bachelor's window: 2025-11-01 to 2025-11-30; Swiss Bachelor's window: 2026-04-01 to 2026-04-30.",
      "reviewedBy": "codex",
      "reviewedAt": "2026-07-10T16:11:08.297399+00:00"
    },
    {
      "id": "new-programme:eth-applied-mathematics-msc",
      "type": "new-programme",
      "status": "approved",
      "universityId": "eth-zurich-swiss-federal-institute-of-technology",
      "detectedAt": "2026-07-08T06:36:09.250065+00:00",
      "sourceUrl": "https://ethz.ch/content/dam/ethz/common/docs/master-profile/englisch/naturwissenschaften/MSc-Mathematics-Appendix.pdf",
      "programme": {
        "id": "eth-applied-mathematics-msc",
        "universityId": "eth-zurich-swiss-federal-institute-of-technology",
        "name": "MSc Applied Mathematics",
        "degreeType": "MSc",
        "faculty": "Natural Sciences and Mathematics | Applied Mathematics",
        "applicationUrl": "https://ethz.ch/en/studies/master/application.html",
        "sourceUrl": "https://ethz.ch/content/dam/ethz/common/docs/master-profile/englisch/naturwissenschaften/MSc-Mathematics-Appendix.pdf"
      },
      "windows": [
        {
          "intake": "Autumn 2026",
          "round": "International Bachelor's window",
          "applicantCategories": [
            "international-bachelors",
            "esop",
            "direct-doctorate"
          ],
          "opensAt": "2025-11-01",
          "opensAtBasis": "official",
          "closesAt": "2025-11-30"
        },
        {
          "intake": "Autumn 2026",
          "round": "Swiss Bachelor's window",
          "applicantCategories": [
            "swiss-bachelors"
          ],
          "opensAt": "2026-04-01",
          "opensAtBasis": "official",
          "closesAt": "2026-04-30"
        }
      ],
      "parseStatus": "parsed",
      "reviewReason": "Review the automatically discovered programme and application rounds.",
      "evidenceExcerpt": "ETH Zurich lists Applied Mathematics MSc in its official profiles of requirements. The official application dates page lists Autumn 2026 master's application windows: International Bachelor's window: 2025-11-01 to 2025-11-30; Swiss Bachelor's window: 2026-04-01 to 2026-04-30.",
      "reviewedBy": "codex",
      "reviewedAt": "2026-07-10T16:11:08.297399+00:00"
    },
    {
      "id": "new-programme:eth-architecture-msc",
      "type": "new-programme",
      "status": "approved",
      "universityId": "eth-zurich-swiss-federal-institute-of-technology",
      "detectedAt": "2026-07-08T06:36:09.250065+00:00",
      "sourceUrl": "https://ethz.ch/content/dam/ethz/common/docs/master-profile/englisch/arch-baug/MSc-Architecture-Appendix.pdf",
      "programme": {
        "id": "eth-architecture-msc",
        "universityId": "eth-zurich-swiss-federal-institute-of-technology",
        "name": "MSc Architecture",
        "degreeType": "MSc",
        "faculty": "Architecture and Civil Engineering | Architecture",
        "applicationUrl": "https://ethz.ch/en/studies/master/application.html",
        "sourceUrl": "https://ethz.ch/content/dam/ethz/common/docs/master-profile/englisch/arch-baug/MSc-Architecture-Appendix.pdf"
      },
      "windows": [
        {
          "intake": "Autumn 2026",
          "round": "International Bachelor's window",
          "applicantCategories": [
            "international-bachelors",
            "esop",
            "direct-doctorate"
          ],
          "opensAt": "2025-11-01",
          "opensAtBasis": "official",
          "closesAt": "2025-11-30"
        },
        {
          "intake": "Autumn 2026",
          "round": "Swiss Bachelor's window",
          "applicantCategories": [
            "swiss-bachelors"
          ],
          "opensAt": "2026-04-01",
          "opensAtBasis": "official",
          "closesAt": "2026-04-30"
        }
      ],
      "parseStatus": "parsed",
      "reviewReason": "Review the automatically discovered programme and application rounds.",
      "evidenceExcerpt": "ETH Zurich lists Architecture MSc in its official profiles of requirements. The official application dates page lists Autumn 2026 master's application windows: International Bachelor's window: 2025-11-01 to 2025-11-30; Swiss Bachelor's window: 2026-04-01 to 2026-04-30.",
      "reviewedBy": "codex",
      "reviewedAt": "2026-07-10T16:11:08.297399+00:00"
    },
    {
      "id": "new-programme:eth-atmospheric-and-climate-science-msc",
      "type": "new-programme",
      "status": "approved",
      "universityId": "eth-zurich-swiss-federal-institute-of-technology",
      "detectedAt": "2026-07-08T06:36:09.250065+00:00",
      "sourceUrl": "https://ethz.ch/content/dam/ethz/common/docs/master-profile/englisch/systemorientierte-wissenschaften/MSc-Atmospheric-Climate-Science-Appendix.pdf",
      "programme": {
        "id": "eth-atmospheric-and-climate-science-msc",
        "universityId": "eth-zurich-swiss-federal-institute-of-technology",
        "name": "MSc Atmospheric and Climate Science",
        "degreeType": "MSc",
        "faculty": "System-oriented Natural Sciences | Atmospheric and Climate Science",
        "applicationUrl": "https://ethz.ch/en/studies/master/application.html",
        "sourceUrl": "https://ethz.ch/content/dam/ethz/common/docs/master-profile/englisch/systemorientierte-wissenschaften/MSc-Atmospheric-Climate-Science-Appendix.pdf"
      },
      "windows": [
        {
          "intake": "Autumn 2026",
          "round": "International Bachelor's window",
          "applicantCategories": [
            "international-bachelors",
            "esop",
            "direct-doctorate"
          ],
          "opensAt": "2025-11-01",
          "opensAtBasis": "official",
          "closesAt": "2025-11-30"
        },
        {
          "intake": "Autumn 2026",
          "round": "Swiss Bachelor's window",
          "applicantCategories": [
            "swiss-bachelors"
          ],
          "opensAt": "2026-04-01",
          "opensAtBasis": "official",
          "closesAt": "2026-04-30"
        }
      ],
      "parseStatus": "parsed",
      "reviewReason": "Review the automatically discovered programme and application rounds.",
      "evidenceExcerpt": "ETH Zurich lists Atmospheric and Climate Science MSc in its official profiles of requirements. The official application dates page lists Autumn 2026 master's application windows: International Bachelor's window: 2025-11-01 to 2025-11-30; Swiss Bachelor's window: 2026-04-01 to 2026-04-30.",
      "reviewedBy": "codex",
      "reviewedAt": "2026-07-10T16:11:08.297399+00:00"
    },
    {
      "id": "new-programme:eth-biochemistry-chemical-biology-msc",
      "type": "new-programme",
      "status": "approved",
      "universityId": "eth-zurich-swiss-federal-institute-of-technology",
      "detectedAt": "2026-07-08T06:36:09.250065+00:00",
      "sourceUrl": "https://ethz.ch/content/dam/ethz/common/docs/master-profile/englisch/naturwissenschaften/MSc-Biochemistry-Appendix.pdf",
      "programme": {
        "id": "eth-biochemistry-chemical-biology-msc",
        "universityId": "eth-zurich-swiss-federal-institute-of-technology",
        "name": "MSc Biochemistry – Chemical Biology",
        "degreeType": "MSc",
        "faculty": "Natural Sciences and Mathematics | Biochemistry – Chemical Biology",
        "applicationUrl": "https://ethz.ch/en/studies/master/application.html",
        "sourceUrl": "https://ethz.ch/content/dam/ethz/common/docs/master-profile/englisch/naturwissenschaften/MSc-Biochemistry-Appendix.pdf"
      },
      "windows": [
        {
          "intake": "Autumn 2026",
          "round": "International Bachelor's window",
          "applicantCategories": [
            "international-bachelors",
            "esop",
            "direct-doctorate"
          ],
          "opensAt": "2025-11-01",
          "opensAtBasis": "official",
          "closesAt": "2025-11-30"
        },
        {
          "intake": "Autumn 2026",
          "round": "Swiss Bachelor's window",
          "applicantCategories": [
            "swiss-bachelors"
          ],
          "opensAt": "2026-04-01",
          "opensAtBasis": "official",
          "closesAt": "2026-04-30"
        }
      ],
      "parseStatus": "parsed",
      "reviewReason": "Review the automatically discovered programme and application rounds.",
      "evidenceExcerpt": "ETH Zurich lists Biochemistry – Chemical Biology MSc in its official profiles of requirements. The official application dates page lists Autumn 2026 master's application windows: International Bachelor's window: 2025-11-01 to 2025-11-30; Swiss Bachelor's window: 2026-04-01 to 2026-04-30.",
      "reviewedBy": "codex",
      "reviewedAt": "2026-07-10T16:11:08.297399+00:00"
    },
    {
      "id": "new-programme:eth-biology-msc",
      "type": "new-programme",
      "status": "approved",
      "universityId": "eth-zurich-swiss-federal-institute-of-technology",
      "detectedAt": "2026-07-08T06:36:09.250065+00:00",
      "sourceUrl": "https://ethz.ch/content/dam/ethz/common/docs/master-profile/englisch/naturwissenschaften/MSc-Biology-Appendix.pdf",
      "programme": {
        "id": "eth-biology-msc",
        "universityId": "eth-zurich-swiss-federal-institute-of-technology",
        "name": "MSc Biology",
        "degreeType": "MSc",
        "faculty": "Natural Sciences and Mathematics | Biology",
        "applicationUrl": "https://ethz.ch/en/studies/master/application.html",
        "sourceUrl": "https://ethz.ch/content/dam/ethz/common/docs/master-profile/englisch/naturwissenschaften/MSc-Biology-Appendix.pdf"
      },
      "windows": [
        {
          "intake": "Autumn 2026",
          "round": "International Bachelor's window",
          "applicantCategories": [
            "international-bachelors",
            "esop",
            "direct-doctorate"
          ],
          "opensAt": "2025-11-01",
          "opensAtBasis": "official",
          "closesAt": "2025-11-30"
        },
        {
          "intake": "Autumn 2026",
          "round": "Swiss Bachelor's window",
          "applicantCategories": [
            "swiss-bachelors"
          ],
          "opensAt": "2026-04-01",
          "opensAtBasis": "official",
          "closesAt": "2026-04-30"
        }
      ],
      "parseStatus": "parsed",
      "reviewReason": "Review the automatically discovered programme and application rounds.",
      "evidenceExcerpt": "ETH Zurich lists Biology MSc in its official profiles of requirements. The official application dates page lists Autumn 2026 master's application windows: International Bachelor's window: 2025-11-01 to 2025-11-30; Swiss Bachelor's window: 2026-04-01 to 2026-04-30.",
      "reviewedBy": "codex",
      "reviewedAt": "2026-07-10T16:11:08.297399+00:00"
    },
    {
      "id": "new-programme:eth-biomedical-engineering-msc",
      "type": "new-programme",
      "status": "approved",
      "universityId": "eth-zurich-swiss-federal-institute-of-technology",
      "detectedAt": "2026-07-08T06:36:09.250065+00:00",
      "sourceUrl": "https://ethz.ch/content/dam/ethz/common/docs/master-profile/englisch/ingenieurwissenschaften/MSc-Biomedical-Engineering-Appendix.pdf",
      "programme": {
        "id": "eth-biomedical-engineering-msc",
        "universityId": "eth-zurich-swiss-federal-institute-of-technology",
        "name": "MSc Biomedical Engineering",
        "degreeType": "MSc",
        "faculty": "Engineering Sciences | Biomedical Engineering",
        "applicationUrl": "https://ethz.ch/en/studies/master/application.html",
        "sourceUrl": "https://ethz.ch/content/dam/ethz/common/docs/master-profile/englisch/ingenieurwissenschaften/MSc-Biomedical-Engineering-Appendix.pdf"
      },
      "windows": [
        {
          "intake": "Autumn 2026",
          "round": "International Bachelor's window",
          "applicantCategories": [
            "international-bachelors",
            "esop",
            "direct-doctorate"
          ],
          "opensAt": "2025-11-01",
          "opensAtBasis": "official",
          "closesAt": "2025-11-30"
        },
        {
          "intake": "Autumn 2026",
          "round": "Swiss Bachelor's window",
          "applicantCategories": [
            "swiss-bachelors"
          ],
          "opensAt": "2026-04-01",
          "opensAtBasis": "official",
          "closesAt": "2026-04-30"
        }
      ],
      "parseStatus": "parsed",
      "reviewReason": "Review the automatically discovered programme and application rounds.",
      "evidenceExcerpt": "ETH Zurich lists Biomedical Engineering MSc in its official profiles of requirements. The official application dates page lists Autumn 2026 master's application windows: International Bachelor's window: 2025-11-01 to 2025-11-30; Swiss Bachelor's window: 2026-04-01 to 2026-04-30.",
      "reviewedBy": "codex",
      "reviewedAt": "2026-07-10T16:11:08.297399+00:00"
    },
    {
      "id": "new-programme:eth-biotechnology-msc",
      "type": "new-programme",
      "status": "approved",
      "universityId": "eth-zurich-swiss-federal-institute-of-technology",
      "detectedAt": "2026-07-08T06:36:09.250065+00:00",
      "sourceUrl": "https://ethz.ch/content/dam/ethz/common/docs/master-profile/englisch/naturwissenschaften/MSc-Biotechnology-Appendix.pdf",
      "programme": {
        "id": "eth-biotechnology-msc",
        "universityId": "eth-zurich-swiss-federal-institute-of-technology",
        "name": "MSc Biotechnology",
        "degreeType": "MSc",
        "faculty": "Natural Sciences and Mathematics | Biotechnology",
        "applicationUrl": "https://ethz.ch/en/studies/master/application.html",
        "sourceUrl": "https://ethz.ch/content/dam/ethz/common/docs/master-profile/englisch/naturwissenschaften/MSc-Biotechnology-Appendix.pdf"
      },
      "windows": [
        {
          "intake": "Autumn 2026",
          "round": "International Bachelor's window",
          "applicantCategories": [
            "international-bachelors",
            "esop",
            "direct-doctorate"
          ],
          "opensAt": "2025-11-01",
          "opensAtBasis": "official",
          "closesAt": "2025-11-30"
        },
        {
          "intake": "Autumn 2026",
          "round": "Swiss Bachelor's window",
          "applicantCategories": [
            "swiss-bachelors"
          ],
          "opensAt": "2026-04-01",
          "opensAtBasis": "official",
          "closesAt": "2026-04-30"
        }
      ],
      "parseStatus": "parsed",
      "reviewReason": "Review the automatically discovered programme and application rounds.",
      "evidenceExcerpt": "ETH Zurich lists Biotechnology MSc in its official profiles of requirements. The official application dates page lists Autumn 2026 master's application windows: International Bachelor's window: 2025-11-01 to 2025-11-30; Swiss Bachelor's window: 2026-04-01 to 2026-04-30.",
      "reviewedBy": "codex",
      "reviewedAt": "2026-07-10T16:11:08.297399+00:00"
    },
    {
      "id": "new-programme:eth-chemical-and-bioengineering-msc",
      "type": "new-programme",
      "status": "approved",
      "universityId": "eth-zurich-swiss-federal-institute-of-technology",
      "detectedAt": "2026-07-08T06:36:09.250065+00:00",
      "sourceUrl": "https://ethz.ch/content/dam/ethz/common/docs/master-profile/englisch/naturwissenschaften/MSc-Chemical-Bioengineering-Appendix.pdf",
      "programme": {
        "id": "eth-chemical-and-bioengineering-msc",
        "universityId": "eth-zurich-swiss-federal-institute-of-technology",
        "name": "MSc Chemical and Bioengineering",
        "degreeType": "MSc",
        "faculty": "Natural Sciences and Mathematics | Chemical and Bioengineering",
        "applicationUrl": "https://ethz.ch/en/studies/master/application.html",
        "sourceUrl": "https://ethz.ch/content/dam/ethz/common/docs/master-profile/englisch/naturwissenschaften/MSc-Chemical-Bioengineering-Appendix.pdf"
      },
      "windows": [
        {
          "intake": "Autumn 2026",
          "round": "International Bachelor's window",
          "applicantCategories": [
            "international-bachelors",
            "esop",
            "direct-doctorate"
          ],
          "opensAt": "2025-11-01",
          "opensAtBasis": "official",
          "closesAt": "2025-11-30"
        },
        {
          "intake": "Autumn 2026",
          "round": "Swiss Bachelor's window",
          "applicantCategories": [
            "swiss-bachelors"
          ],
          "opensAt": "2026-04-01",
          "opensAtBasis": "official",
          "closesAt": "2026-04-30"
        }
      ],
      "parseStatus": "parsed",
      "reviewReason": "Review the automatically discovered programme and application rounds.",
      "evidenceExcerpt": "ETH Zurich lists Chemical and Bioengineering MSc in its official profiles of requirements. The official application dates page lists Autumn 2026 master's application windows: International Bachelor's window: 2025-11-01 to 2025-11-30; Swiss Bachelor's window: 2026-04-01 to 2026-04-30.",
      "reviewedBy": "codex",
      "reviewedAt": "2026-07-10T16:11:08.297399+00:00"
    },
    {
      "id": "new-programme:eth-chemistry-msc",
      "type": "new-programme",
      "status": "approved",
      "universityId": "eth-zurich-swiss-federal-institute-of-technology",
      "detectedAt": "2026-07-08T06:36:09.250065+00:00",
      "sourceUrl": "https://ethz.ch/content/dam/ethz/common/docs/master-profile/englisch/naturwissenschaften/MSc-Chemistry-Appendix.pdf",
      "programme": {
        "id": "eth-chemistry-msc",
        "universityId": "eth-zurich-swiss-federal-institute-of-technology",
        "name": "MSc Chemistry",
        "degreeType": "MSc",
        "faculty": "Natural Sciences and Mathematics | Chemistry",
        "applicationUrl": "https://ethz.ch/en/studies/master/application.html",
        "sourceUrl": "https://ethz.ch/content/dam/ethz/common/docs/master-profile/englisch/naturwissenschaften/MSc-Chemistry-Appendix.pdf"
      },
      "windows": [
        {
          "intake": "Autumn 2026",
          "round": "International Bachelor's window",
          "applicantCategories": [
            "international-bachelors",
            "esop",
            "direct-doctorate"
          ],
          "opensAt": "2025-11-01",
          "opensAtBasis": "official",
          "closesAt": "2025-11-30"
        },
        {
          "intake": "Autumn 2026",
          "round": "Swiss Bachelor's window",
          "applicantCategories": [
            "swiss-bachelors"
          ],
          "opensAt": "2026-04-01",
          "opensAtBasis": "official",
          "closesAt": "2026-04-30"
        }
      ],
      "parseStatus": "parsed",
      "reviewReason": "Review the automatically discovered programme and application rounds.",
      "evidenceExcerpt": "ETH Zurich lists Chemistry MSc in its official profiles of requirements. The official application dates page lists Autumn 2026 master's application windows: International Bachelor's window: 2025-11-01 to 2025-11-30; Swiss Bachelor's window: 2026-04-01 to 2026-04-30.",
      "reviewedBy": "codex",
      "reviewedAt": "2026-07-10T16:11:08.297399+00:00"
    },
    {
      "id": "new-programme:eth-civil-engineering-msc",
      "type": "new-programme",
      "status": "approved",
      "universityId": "eth-zurich-swiss-federal-institute-of-technology",
      "detectedAt": "2026-07-08T06:36:09.250065+00:00",
      "sourceUrl": "https://ethz.ch/content/dam/ethz/common/docs/master-profile/englisch/arch-baug/MSc-Civil-Engineering-Appendix.pdf",
      "programme": {
        "id": "eth-civil-engineering-msc",
        "universityId": "eth-zurich-swiss-federal-institute-of-technology",
        "name": "MSc Civil Engineering",
        "degreeType": "MSc",
        "faculty": "Architecture and Civil Engineering | Civil Engineering",
        "applicationUrl": "https://ethz.ch/en/studies/master/application.html",
        "sourceUrl": "https://ethz.ch/content/dam/ethz/common/docs/master-profile/englisch/arch-baug/MSc-Civil-Engineering-Appendix.pdf"
      },
      "windows": [
        {
          "intake": "Autumn 2026",
          "round": "International Bachelor's window",
          "applicantCategories": [
            "international-bachelors",
            "esop",
            "direct-doctorate"
          ],
          "opensAt": "2025-11-01",
          "opensAtBasis": "official",
          "closesAt": "2025-11-30"
        },
        {
          "intake": "Autumn 2026",
          "round": "Swiss Bachelor's window",
          "applicantCategories": [
            "swiss-bachelors"
          ],
          "opensAt": "2026-04-01",
          "opensAtBasis": "official",
          "closesAt": "2026-04-30"
        }
      ],
      "parseStatus": "parsed",
      "reviewReason": "Review the automatically discovered programme and application rounds.",
      "evidenceExcerpt": "ETH Zurich lists Civil Engineering MSc in its official profiles of requirements. The official application dates page lists Autumn 2026 master's application windows: International Bachelor's window: 2025-11-01 to 2025-11-30; Swiss Bachelor's window: 2026-04-01 to 2026-04-30.",
      "reviewedBy": "codex",
      "reviewedAt": "2026-07-10T16:11:08.297399+00:00"
    },
    {
      "id": "new-programme:eth-comparative-and-international-studies-ma",
      "type": "new-programme",
      "status": "approved",
      "universityId": "eth-zurich-swiss-federal-institute-of-technology",
      "detectedAt": "2026-07-08T06:36:09.250065+00:00",
      "sourceUrl": "https://ethz.ch/content/dam/ethz/common/docs/master-profile/englisch/management-sozialwissenschaften/MA-CIS-Appendix.pdf",
      "programme": {
        "id": "eth-comparative-and-international-studies-ma",
        "universityId": "eth-zurich-swiss-federal-institute-of-technology",
        "name": "MA Comparative and International Studies",
        "degreeType": "MA",
        "faculty": "Management and Social Sciences | Comparative and International Studies",
        "applicationUrl": "https://ethz.ch/en/studies/master/application.html",
        "sourceUrl": "https://ethz.ch/content/dam/ethz/common/docs/master-profile/englisch/management-sozialwissenschaften/MA-CIS-Appendix.pdf"
      },
      "windows": [
        {
          "intake": "Autumn 2026",
          "round": "International Bachelor's window",
          "applicantCategories": [
            "international-bachelors",
            "esop",
            "direct-doctorate"
          ],
          "opensAt": "2025-11-01",
          "opensAtBasis": "official",
          "closesAt": "2025-11-30"
        },
        {
          "intake": "Autumn 2026",
          "round": "Swiss Bachelor's window",
          "applicantCategories": [
            "swiss-bachelors"
          ],
          "opensAt": "2026-04-01",
          "opensAtBasis": "official",
          "closesAt": "2026-04-30"
        }
      ],
      "parseStatus": "parsed",
      "reviewReason": "Review the automatically discovered programme and application rounds.",
      "evidenceExcerpt": "ETH Zurich lists Comparative and International Studies MA in its official profiles of requirements. The official application dates page lists Autumn 2026 master's application windows: International Bachelor's window: 2025-11-01 to 2025-11-30; Swiss Bachelor's window: 2026-04-01 to 2026-04-30.",
      "reviewedBy": "codex",
      "reviewedAt": "2026-07-10T16:11:08.297399+00:00"
    },
    {
      "id": "new-programme:eth-computational-biology-and-bioinformatics-msc",
      "type": "new-programme",
      "status": "approved",
      "universityId": "eth-zurich-swiss-federal-institute-of-technology",
      "detectedAt": "2026-07-08T06:36:09.250065+00:00",
      "sourceUrl": "https://ethz.ch/content/dam/ethz/common/docs/master-profile/englisch/ingenieurwissenschaften/MSc-CBB-Appendix.pdf",
      "programme": {
        "id": "eth-computational-biology-and-bioinformatics-msc",
        "universityId": "eth-zurich-swiss-federal-institute-of-technology",
        "name": "MSc Computational Biology and Bioinformatics",
        "degreeType": "MSc",
        "faculty": "Engineering Sciences | Computational Biology and Bioinformatics",
        "applicationUrl": "https://ethz.ch/en/studies/master/application.html",
        "sourceUrl": "https://ethz.ch/content/dam/ethz/common/docs/master-profile/englisch/ingenieurwissenschaften/MSc-CBB-Appendix.pdf"
      },
      "windows": [
        {
          "intake": "Autumn 2026",
          "round": "International Bachelor's window",
          "applicantCategories": [
            "international-bachelors",
            "esop",
            "direct-doctorate"
          ],
          "opensAt": "2025-11-01",
          "opensAtBasis": "official",
          "closesAt": "2025-11-30"
        },
        {
          "intake": "Autumn 2026",
          "round": "Swiss Bachelor's window",
          "applicantCategories": [
            "swiss-bachelors"
          ],
          "opensAt": "2026-04-01",
          "opensAtBasis": "official",
          "closesAt": "2026-04-30"
        }
      ],
      "parseStatus": "parsed",
      "reviewReason": "Review the automatically discovered programme and application rounds.",
      "evidenceExcerpt": "ETH Zurich lists Computational Biology and Bioinformatics MSc in its official profiles of requirements. The official application dates page lists Autumn 2026 master's application windows: International Bachelor's window: 2025-11-01 to 2025-11-30; Swiss Bachelor's window: 2026-04-01 to 2026-04-30.",
      "reviewedBy": "codex",
      "reviewedAt": "2026-07-10T16:11:08.297399+00:00"
    },
    {
      "id": "new-programme:eth-computational-science-and-engineering-msc",
      "type": "new-programme",
      "status": "approved",
      "universityId": "eth-zurich-swiss-federal-institute-of-technology",
      "detectedAt": "2026-07-08T06:36:09.250065+00:00",
      "sourceUrl": "https://ethz.ch/content/dam/ethz/common/docs/master-profile/englisch/naturwissenschaften/MSc-Computational-Science-Engineering-Appendix.pdf",
      "programme": {
        "id": "eth-computational-science-and-engineering-msc",
        "universityId": "eth-zurich-swiss-federal-institute-of-technology",
        "name": "MSc Computational Science and Engineering",
        "degreeType": "MSc",
        "faculty": "Natural Sciences and Mathematics | Computational Science and Engineering",
        "applicationUrl": "https://ethz.ch/en/studies/master/application.html",
        "sourceUrl": "https://ethz.ch/content/dam/ethz/common/docs/master-profile/englisch/naturwissenschaften/MSc-Computational-Science-Engineering-Appendix.pdf"
      },
      "windows": [
        {
          "intake": "Autumn 2026",
          "round": "International Bachelor's window",
          "applicantCategories": [
            "international-bachelors",
            "esop",
            "direct-doctorate"
          ],
          "opensAt": "2025-11-01",
          "opensAtBasis": "official",
          "closesAt": "2025-11-30"
        },
        {
          "intake": "Autumn 2026",
          "round": "Swiss Bachelor's window",
          "applicantCategories": [
            "swiss-bachelors"
          ],
          "opensAt": "2026-04-01",
          "opensAtBasis": "official",
          "closesAt": "2026-04-30"
        }
      ],
      "parseStatus": "parsed",
      "reviewReason": "Review the automatically discovered programme and application rounds.",
      "evidenceExcerpt": "ETH Zurich lists Computational Science and Engineering MSc in its official profiles of requirements. The official application dates page lists Autumn 2026 master's application windows: International Bachelor's window: 2025-11-01 to 2025-11-30; Swiss Bachelor's window: 2026-04-01 to 2026-04-30.",
      "reviewedBy": "codex",
      "reviewedAt": "2026-07-10T16:11:08.297399+00:00"
    },
    {
      "id": "new-programme:eth-cyber-security-msc",
      "type": "new-programme",
      "status": "approved",
      "universityId": "eth-zurich-swiss-federal-institute-of-technology",
      "detectedAt": "2026-07-08T06:36:09.250065+00:00",
      "sourceUrl": "https://ethz.ch/content/dam/ethz/common/docs/master-profile/englisch/ingenieurwissenschaften/MSc%20Cyber%20Security%20Appendix_Regulations.pdf",
      "programme": {
        "id": "eth-cyber-security-msc",
        "universityId": "eth-zurich-swiss-federal-institute-of-technology",
        "name": "MSc Cyber Security",
        "degreeType": "MSc",
        "faculty": "Engineering Sciences | Cyber Security",
        "applicationUrl": "https://ethz.ch/en/studies/master/application.html",
        "sourceUrl": "https://ethz.ch/content/dam/ethz/common/docs/master-profile/englisch/ingenieurwissenschaften/MSc%20Cyber%20Security%20Appendix_Regulations.pdf"
      },
      "windows": [
        {
          "intake": "Autumn 2026",
          "round": "International Bachelor's window",
          "applicantCategories": [
            "international-bachelors",
            "esop",
            "direct-doctorate"
          ],
          "opensAt": "2025-11-01",
          "opensAtBasis": "official",
          "closesAt": "2025-11-30"
        },
        {
          "intake": "Autumn 2026",
          "round": "Swiss Bachelor's window",
          "applicantCategories": [
            "swiss-bachelors"
          ],
          "opensAt": "2026-04-01",
          "opensAtBasis": "official",
          "closesAt": "2026-04-30"
        }
      ],
      "parseStatus": "parsed",
      "reviewReason": "Review the automatically discovered programme and application rounds.",
      "evidenceExcerpt": "ETH Zurich lists Cyber Security MSc in its official profiles of requirements. The official application dates page lists Autumn 2026 master's application windows: International Bachelor's window: 2025-11-01 to 2025-11-30; Swiss Bachelor's window: 2026-04-01 to 2026-04-30.",
      "reviewedBy": "codex",
      "reviewedAt": "2026-07-10T16:11:08.297399+00:00"
    },
    {
      "id": "new-programme:eth-earth-sciences-msc",
      "type": "new-programme",
      "status": "approved",
      "universityId": "eth-zurich-swiss-federal-institute-of-technology",
      "detectedAt": "2026-07-08T06:36:09.250065+00:00",
      "sourceUrl": "https://ethz.ch/content/dam/ethz/common/docs/master-profile/englisch/systemorientierte-wissenschaften/MSc-Earth-Sciences-Appendix.pdf",
      "programme": {
        "id": "eth-earth-sciences-msc",
        "universityId": "eth-zurich-swiss-federal-institute-of-technology",
        "name": "MSc Earth Sciences",
        "degreeType": "MSc",
        "faculty": "System-oriented Natural Sciences | Earth Sciences",
        "applicationUrl": "https://ethz.ch/en/studies/master/application.html",
        "sourceUrl": "https://ethz.ch/content/dam/ethz/common/docs/master-profile/englisch/systemorientierte-wissenschaften/MSc-Earth-Sciences-Appendix.pdf"
      },
      "windows": [
        {
          "intake": "Autumn 2026",
          "round": "International Bachelor's window",
          "applicantCategories": [
            "international-bachelors",
            "esop",
            "direct-doctorate"
          ],
          "opensAt": "2025-11-01",
          "opensAtBasis": "official",
          "closesAt": "2025-11-30"
        },
        {
          "intake": "Autumn 2026",
          "round": "Swiss Bachelor's window",
          "applicantCategories": [
            "swiss-bachelors"
          ],
          "opensAt": "2026-04-01",
          "opensAtBasis": "official",
          "closesAt": "2026-04-30"
        }
      ],
      "parseStatus": "parsed",
      "reviewReason": "Review the automatically discovered programme and application rounds.",
      "evidenceExcerpt": "ETH Zurich lists Earth Sciences MSc in its official profiles of requirements. The official application dates page lists Autumn 2026 master's application windows: International Bachelor's window: 2025-11-01 to 2025-11-30; Swiss Bachelor's window: 2026-04-01 to 2026-04-30.",
      "reviewedBy": "codex",
      "reviewedAt": "2026-07-10T16:11:08.297399+00:00"
    },
    {
      "id": "new-programme:eth-electrical-engineering-and-information-technology-msc",
      "type": "new-programme",
      "status": "approved",
      "universityId": "eth-zurich-swiss-federal-institute-of-technology",
      "detectedAt": "2026-07-08T06:36:09.250065+00:00",
      "sourceUrl": "https://ethz.ch/content/dam/ethz/common/docs/master-profile/englisch/ingenieurwissenschaften/MSc-ETIT-Appendix.pdf",
      "programme": {
        "id": "eth-electrical-engineering-and-information-technology-msc",
        "universityId": "eth-zurich-swiss-federal-institute-of-technology",
        "name": "MSc Electrical Engineering and Information Technology",
        "degreeType": "MSc",
        "faculty": "Engineering Sciences | Electrical Engineering and Information Technology",
        "applicationUrl": "https://ethz.ch/en/studies/master/application.html",
        "sourceUrl": "https://ethz.ch/content/dam/ethz/common/docs/master-profile/englisch/ingenieurwissenschaften/MSc-ETIT-Appendix.pdf"
      },
      "windows": [
        {
          "intake": "Autumn 2026",
          "round": "International Bachelor's window",
          "applicantCategories": [
            "international-bachelors",
            "esop",
            "direct-doctorate"
          ],
          "opensAt": "2025-11-01",
          "opensAtBasis": "official",
          "closesAt": "2025-11-30"
        },
        {
          "intake": "Autumn 2026",
          "round": "Swiss Bachelor's window",
          "applicantCategories": [
            "swiss-bachelors"
          ],
          "opensAt": "2026-04-01",
          "opensAtBasis": "official",
          "closesAt": "2026-04-30"
        }
      ],
      "parseStatus": "parsed",
      "reviewReason": "Review the automatically discovered programme and application rounds.",
      "evidenceExcerpt": "ETH Zurich lists Electrical Engineering and Information Technology MSc in its official profiles of requirements. The official application dates page lists Autumn 2026 master's application windows: International Bachelor's window: 2025-11-01 to 2025-11-30; Swiss Bachelor's window: 2026-04-01 to 2026-04-30.",
      "reviewedBy": "codex",
      "reviewedAt": "2026-07-10T16:11:08.297399+00:00"
    },
    {
      "id": "new-programme:eth-energy-science-and-technology-msc",
      "type": "new-programme",
      "status": "approved",
      "universityId": "eth-zurich-swiss-federal-institute-of-technology",
      "detectedAt": "2026-07-08T06:36:09.250065+00:00",
      "sourceUrl": "https://ethz.ch/content/dam/ethz/common/docs/master-profile/englisch/ingenieurwissenschaften/MSc-Energy-Science-Technology-Appendix.pdf",
      "programme": {
        "id": "eth-energy-science-and-technology-msc",
        "universityId": "eth-zurich-swiss-federal-institute-of-technology",
        "name": "MSc Energy Science and Technology",
        "degreeType": "MSc",
        "faculty": "Engineering Sciences | Energy Science and Technology",
        "applicationUrl": "https://ethz.ch/en/studies/master/application.html",
        "sourceUrl": "https://ethz.ch/content/dam/ethz/common/docs/master-profile/englisch/ingenieurwissenschaften/MSc-Energy-Science-Technology-Appendix.pdf"
      },
      "windows": [
        {
          "intake": "Autumn 2026",
          "round": "International Bachelor's window",
          "applicantCategories": [
            "international-bachelors",
            "esop",
            "direct-doctorate"
          ],
          "opensAt": "2025-11-01",
          "opensAtBasis": "official",
          "closesAt": "2025-11-30"
        },
        {
          "intake": "Autumn 2026",
          "round": "Swiss Bachelor's window",
          "applicantCategories": [
            "swiss-bachelors"
          ],
          "opensAt": "2026-04-01",
          "opensAtBasis": "official",
          "closesAt": "2026-04-30"
        }
      ],
      "parseStatus": "parsed",
      "reviewReason": "Review the automatically discovered programme and application rounds.",
      "evidenceExcerpt": "ETH Zurich lists Energy Science and Technology MSc in its official profiles of requirements. The official application dates page lists Autumn 2026 master's application windows: International Bachelor's window: 2025-11-01 to 2025-11-30; Swiss Bachelor's window: 2026-04-01 to 2026-04-30.",
      "reviewedBy": "codex",
      "reviewedAt": "2026-07-10T16:11:08.297399+00:00"
    },
    {
      "id": "new-programme:eth-environmental-engineering-msc",
      "type": "new-programme",
      "status": "approved",
      "universityId": "eth-zurich-swiss-federal-institute-of-technology",
      "detectedAt": "2026-07-08T06:36:09.250065+00:00",
      "sourceUrl": "https://ethz.ch/content/dam/ethz/common/docs/master-profile/englisch/arch-baug/MSc-Environmental-Engineering-Appendix.pdf",
      "programme": {
        "id": "eth-environmental-engineering-msc",
        "universityId": "eth-zurich-swiss-federal-institute-of-technology",
        "name": "MSc Environmental Engineering",
        "degreeType": "MSc",
        "faculty": "Architecture and Civil Engineering | Environmental Engineering",
        "applicationUrl": "https://ethz.ch/en/studies/master/application.html",
        "sourceUrl": "https://ethz.ch/content/dam/ethz/common/docs/master-profile/englisch/arch-baug/MSc-Environmental-Engineering-Appendix.pdf"
      },
      "windows": [
        {
          "intake": "Autumn 2026",
          "round": "International Bachelor's window",
          "applicantCategories": [
            "international-bachelors",
            "esop",
            "direct-doctorate"
          ],
          "opensAt": "2025-11-01",
          "opensAtBasis": "official",
          "closesAt": "2025-11-30"
        },
        {
          "intake": "Autumn 2026",
          "round": "Swiss Bachelor's window",
          "applicantCategories": [
            "swiss-bachelors"
          ],
          "opensAt": "2026-04-01",
          "opensAtBasis": "official",
          "closesAt": "2026-04-30"
        }
      ],
      "parseStatus": "parsed",
      "reviewReason": "Review the automatically discovered programme and application rounds.",
      "evidenceExcerpt": "ETH Zurich lists Environmental Engineering MSc in its official profiles of requirements. The official application dates page lists Autumn 2026 master's application windows: International Bachelor's window: 2025-11-01 to 2025-11-30; Swiss Bachelor's window: 2026-04-01 to 2026-04-30.",
      "reviewedBy": "codex",
      "reviewedAt": "2026-07-10T16:11:08.297399+00:00"
    },
    {
      "id": "new-programme:eth-environmental-sciences-msc",
      "type": "new-programme",
      "status": "approved",
      "universityId": "eth-zurich-swiss-federal-institute-of-technology",
      "detectedAt": "2026-07-08T06:36:09.250065+00:00",
      "sourceUrl": "https://ethz.ch/content/dam/ethz/common/docs/master-profile/englisch/systemorientierte-wissenschaften/MSc-Environmental-Sciences-Appendix.pdf",
      "programme": {
        "id": "eth-environmental-sciences-msc",
        "universityId": "eth-zurich-swiss-federal-institute-of-technology",
        "name": "MSc Environmental Sciences",
        "degreeType": "MSc",
        "faculty": "System-oriented Natural Sciences | Environmental Sciences",
        "applicationUrl": "https://ethz.ch/en/studies/master/application.html",
        "sourceUrl": "https://ethz.ch/content/dam/ethz/common/docs/master-profile/englisch/systemorientierte-wissenschaften/MSc-Environmental-Sciences-Appendix.pdf"
      },
      "windows": [
        {
          "intake": "Autumn 2026",
          "round": "International Bachelor's window",
          "applicantCategories": [
            "international-bachelors",
            "esop",
            "direct-doctorate"
          ],
          "opensAt": "2025-11-01",
          "opensAtBasis": "official",
          "closesAt": "2025-11-30"
        },
        {
          "intake": "Autumn 2026",
          "round": "Swiss Bachelor's window",
          "applicantCategories": [
            "swiss-bachelors"
          ],
          "opensAt": "2026-04-01",
          "opensAtBasis": "official",
          "closesAt": "2026-04-30"
        }
      ],
      "parseStatus": "parsed",
      "reviewReason": "Review the automatically discovered programme and application rounds.",
      "evidenceExcerpt": "ETH Zurich lists Environmental Sciences MSc in its official profiles of requirements. The official application dates page lists Autumn 2026 master's application windows: International Bachelor's window: 2025-11-01 to 2025-11-30; Swiss Bachelor's window: 2026-04-01 to 2026-04-30.",
      "reviewedBy": "codex",
      "reviewedAt": "2026-07-10T16:11:08.297399+00:00"
    },
    {
      "id": "new-programme:eth-food-science-and-nutrition-msc",
      "type": "new-programme",
      "status": "approved",
      "universityId": "eth-zurich-swiss-federal-institute-of-technology",
      "detectedAt": "2026-07-08T06:36:09.250065+00:00",
      "sourceUrl": "https://ethz.ch/content/dam/ethz/common/docs/master-profile/englisch/systemorientierte-wissenschaften/MSc-Food-Science-Appendix.pdf",
      "programme": {
        "id": "eth-food-science-and-nutrition-msc",
        "universityId": "eth-zurich-swiss-federal-institute-of-technology",
        "name": "MSc Food Science and Nutrition",
        "degreeType": "MSc",
        "faculty": "System-oriented Natural Sciences | Food Science and Nutrition",
        "applicationUrl": "https://ethz.ch/en/studies/master/application.html",
        "sourceUrl": "https://ethz.ch/content/dam/ethz/common/docs/master-profile/englisch/systemorientierte-wissenschaften/MSc-Food-Science-Appendix.pdf"
      },
      "windows": [
        {
          "intake": "Autumn 2026",
          "round": "International Bachelor's window",
          "applicantCategories": [
            "international-bachelors",
            "esop",
            "direct-doctorate"
          ],
          "opensAt": "2025-11-01",
          "opensAtBasis": "official",
          "closesAt": "2025-11-30"
        },
        {
          "intake": "Autumn 2026",
          "round": "Swiss Bachelor's window",
          "applicantCategories": [
            "swiss-bachelors"
          ],
          "opensAt": "2026-04-01",
          "opensAtBasis": "official",
          "closesAt": "2026-04-30"
        }
      ],
      "parseStatus": "parsed",
      "reviewReason": "Review the automatically discovered programme and application rounds.",
      "evidenceExcerpt": "ETH Zurich lists Food Science and Nutrition MSc in its official profiles of requirements. The official application dates page lists Autumn 2026 master's application windows: International Bachelor's window: 2025-11-01 to 2025-11-30; Swiss Bachelor's window: 2026-04-01 to 2026-04-30.",
      "reviewedBy": "codex",
      "reviewedAt": "2026-07-10T16:11:08.297399+00:00"
    },
    {
      "id": "new-programme:eth-geomatics-msc",
      "type": "new-programme",
      "status": "approved",
      "universityId": "eth-zurich-swiss-federal-institute-of-technology",
      "detectedAt": "2026-07-08T06:36:09.250065+00:00",
      "sourceUrl": "https://ethz.ch/content/dam/ethz/common/docs/master-profile/englisch/arch-baug/MSc-Geomatics-Appendix.pdf",
      "programme": {
        "id": "eth-geomatics-msc",
        "universityId": "eth-zurich-swiss-federal-institute-of-technology",
        "name": "MSc Geomatics",
        "degreeType": "MSc",
        "faculty": "Architecture and Civil Engineering | Geomatics",
        "applicationUrl": "https://ethz.ch/en/studies/master/application.html",
        "sourceUrl": "https://ethz.ch/content/dam/ethz/common/docs/master-profile/englisch/arch-baug/MSc-Geomatics-Appendix.pdf"
      },
      "windows": [
        {
          "intake": "Autumn 2026",
          "round": "International Bachelor's window",
          "applicantCategories": [
            "international-bachelors",
            "esop",
            "direct-doctorate"
          ],
          "opensAt": "2025-11-01",
          "opensAtBasis": "official",
          "closesAt": "2025-11-30"
        },
        {
          "intake": "Autumn 2026",
          "round": "Swiss Bachelor's window",
          "applicantCategories": [
            "swiss-bachelors"
          ],
          "opensAt": "2026-04-01",
          "opensAtBasis": "official",
          "closesAt": "2026-04-30"
        }
      ],
      "parseStatus": "parsed",
      "reviewReason": "Review the automatically discovered programme and application rounds.",
      "evidenceExcerpt": "ETH Zurich lists Geomatics MSc in its official profiles of requirements. The official application dates page lists Autumn 2026 master's application windows: International Bachelor's window: 2025-11-01 to 2025-11-30; Swiss Bachelor's window: 2026-04-01 to 2026-04-30.",
      "reviewedBy": "codex",
      "reviewedAt": "2026-07-10T16:11:08.297399+00:00"
    },
    {
      "id": "new-programme:eth-health-sciences-and-technology-msc",
      "type": "new-programme",
      "status": "approved",
      "universityId": "eth-zurich-swiss-federal-institute-of-technology",
      "detectedAt": "2026-07-08T06:36:09.250065+00:00",
      "sourceUrl": "https://ethz.ch/content/dam/ethz/common/docs/master-profile/englisch/systemorientierte-wissenschaften/MSc-HST-Appendix.pdf",
      "programme": {
        "id": "eth-health-sciences-and-technology-msc",
        "universityId": "eth-zurich-swiss-federal-institute-of-technology",
        "name": "MSc Health Sciences and Technology",
        "degreeType": "MSc",
        "faculty": "System-oriented Natural Sciences | Health Sciences and Technology",
        "applicationUrl": "https://ethz.ch/en/studies/master/application.html",
        "sourceUrl": "https://ethz.ch/content/dam/ethz/common/docs/master-profile/englisch/systemorientierte-wissenschaften/MSc-HST-Appendix.pdf"
      },
      "windows": [
        {
          "intake": "Autumn 2026",
          "round": "International Bachelor's window",
          "applicantCategories": [
            "international-bachelors",
            "esop",
            "direct-doctorate"
          ],
          "opensAt": "2025-11-01",
          "opensAtBasis": "official",
          "closesAt": "2025-11-30"
        },
        {
          "intake": "Autumn 2026",
          "round": "Swiss Bachelor's window",
          "applicantCategories": [
            "swiss-bachelors"
          ],
          "opensAt": "2026-04-01",
          "opensAtBasis": "official",
          "closesAt": "2026-04-30"
        }
      ],
      "parseStatus": "parsed",
      "reviewReason": "Review the automatically discovered programme and application rounds.",
      "evidenceExcerpt": "ETH Zurich lists Health Sciences and Technology MSc in its official profiles of requirements. The official application dates page lists Autumn 2026 master's application windows: International Bachelor's window: 2025-11-01 to 2025-11-30; Swiss Bachelor's window: 2026-04-01 to 2026-04-30.",
      "reviewedBy": "codex",
      "reviewedAt": "2026-07-10T16:11:08.297399+00:00"
    },
    {
      "id": "new-programme:eth-high-energy-physics-msc",
      "type": "new-programme",
      "status": "approved",
      "universityId": "eth-zurich-swiss-federal-institute-of-technology",
      "detectedAt": "2026-07-08T06:36:09.250065+00:00",
      "sourceUrl": "https://ethz.ch/content/dam/ethz/common/docs/master-profile/englisch/naturwissenschaften/MSc-High-Energy-Physics-Appendix.pdf",
      "programme": {
        "id": "eth-high-energy-physics-msc",
        "universityId": "eth-zurich-swiss-federal-institute-of-technology",
        "name": "MSc High Energy Physics",
        "degreeType": "MSc",
        "faculty": "Natural Sciences and Mathematics | High Energy Physics",
        "applicationUrl": "https://ethz.ch/en/studies/master/application.html",
        "sourceUrl": "https://ethz.ch/content/dam/ethz/common/docs/master-profile/englisch/naturwissenschaften/MSc-High-Energy-Physics-Appendix.pdf"
      },
      "windows": [
        {
          "intake": "Autumn 2026",
          "round": "International Bachelor's window",
          "applicantCategories": [
            "international-bachelors",
            "esop",
            "direct-doctorate"
          ],
          "opensAt": "2025-11-01",
          "opensAtBasis": "official",
          "closesAt": "2025-11-30"
        },
        {
          "intake": "Autumn 2026",
          "round": "Swiss Bachelor's window",
          "applicantCategories": [
            "swiss-bachelors"
          ],
          "opensAt": "2026-04-01",
          "opensAtBasis": "official",
          "closesAt": "2026-04-30"
        }
      ],
      "parseStatus": "parsed",
      "reviewReason": "Review the automatically discovered programme and application rounds.",
      "evidenceExcerpt": "ETH Zurich lists High Energy Physics MSc in its official profiles of requirements. The official application dates page lists Autumn 2026 master's application windows: International Bachelor's window: 2025-11-01 to 2025-11-30; Swiss Bachelor's window: 2026-04-01 to 2026-04-30.",
      "reviewedBy": "codex",
      "reviewedAt": "2026-07-10T16:11:08.297399+00:00"
    },
    {
      "id": "new-programme:eth-history-and-philosophy-of-knowledge-ma",
      "type": "new-programme",
      "status": "approved",
      "universityId": "eth-zurich-swiss-federal-institute-of-technology",
      "detectedAt": "2026-07-08T06:36:09.250065+00:00",
      "sourceUrl": "https://ethz.ch/content/dam/ethz/common/docs/master-profile/englisch/management-sozialwissenschaften/GPW-MA-Appendix.pdf",
      "programme": {
        "id": "eth-history-and-philosophy-of-knowledge-ma",
        "universityId": "eth-zurich-swiss-federal-institute-of-technology",
        "name": "MA History and Philosophy of Knowledge",
        "degreeType": "MA",
        "faculty": "Management and Social Sciences | History and Philosophy of Knowledge",
        "applicationUrl": "https://ethz.ch/en/studies/master/application.html",
        "sourceUrl": "https://ethz.ch/content/dam/ethz/common/docs/master-profile/englisch/management-sozialwissenschaften/GPW-MA-Appendix.pdf"
      },
      "windows": [
        {
          "intake": "Autumn 2026",
          "round": "International Bachelor's window",
          "applicantCategories": [
            "international-bachelors",
            "esop",
            "direct-doctorate"
          ],
          "opensAt": "2025-11-01",
          "opensAtBasis": "official",
          "closesAt": "2025-11-30"
        },
        {
          "intake": "Autumn 2026",
          "round": "Swiss Bachelor's window",
          "applicantCategories": [
            "swiss-bachelors"
          ],
          "opensAt": "2026-04-01",
          "opensAtBasis": "official",
          "closesAt": "2026-04-30"
        }
      ],
      "parseStatus": "parsed",
      "reviewReason": "Review the automatically discovered programme and application rounds.",
      "evidenceExcerpt": "ETH Zurich lists History and Philosophy of Knowledge MA in its official profiles of requirements. The official application dates page lists Autumn 2026 master's application windows: International Bachelor's window: 2025-11-01 to 2025-11-30; Swiss Bachelor's window: 2026-04-01 to 2026-04-30.",
      "reviewedBy": "codex",
      "reviewedAt": "2026-07-10T16:11:08.297399+00:00"
    },
    {
      "id": "new-programme:eth-integrated-building-systems-msc",
      "type": "new-programme",
      "status": "approved",
      "universityId": "eth-zurich-swiss-federal-institute-of-technology",
      "detectedAt": "2026-07-08T06:36:09.250065+00:00",
      "sourceUrl": "https://ethz.ch/content/dam/ethz/common/docs/master-profile/englisch/arch-baug/MSc-IBS-Appendix.pdf",
      "programme": {
        "id": "eth-integrated-building-systems-msc",
        "universityId": "eth-zurich-swiss-federal-institute-of-technology",
        "name": "MSc Integrated Building Systems",
        "degreeType": "MSc",
        "faculty": "Architecture and Civil Engineering | Integrated Building Systems",
        "applicationUrl": "https://ethz.ch/en/studies/master/application.html",
        "sourceUrl": "https://ethz.ch/content/dam/ethz/common/docs/master-profile/englisch/arch-baug/MSc-IBS-Appendix.pdf"
      },
      "windows": [
        {
          "intake": "Autumn 2026",
          "round": "International Bachelor's window",
          "applicantCategories": [
            "international-bachelors",
            "esop",
            "direct-doctorate"
          ],
          "opensAt": "2025-11-01",
          "opensAtBasis": "official",
          "closesAt": "2025-11-30"
        },
        {
          "intake": "Autumn 2026",
          "round": "Swiss Bachelor's window",
          "applicantCategories": [
            "swiss-bachelors"
          ],
          "opensAt": "2026-04-01",
          "opensAtBasis": "official",
          "closesAt": "2026-04-30"
        }
      ],
      "parseStatus": "parsed",
      "reviewReason": "Review the automatically discovered programme and application rounds.",
      "evidenceExcerpt": "ETH Zurich lists Integrated Building Systems MSc in its official profiles of requirements. The official application dates page lists Autumn 2026 master's application windows: International Bachelor's window: 2025-11-01 to 2025-11-30; Swiss Bachelor's window: 2026-04-01 to 2026-04-30.",
      "reviewedBy": "codex",
      "reviewedAt": "2026-07-10T16:11:08.297399+00:00"
    },
    {
      "id": "new-programme:eth-interdisciplinary-sciences-msc",
      "type": "new-programme",
      "status": "approved",
      "universityId": "eth-zurich-swiss-federal-institute-of-technology",
      "detectedAt": "2026-07-08T06:36:09.250065+00:00",
      "sourceUrl": "https://ethz.ch/content/dam/ethz/common/docs/master-profile/englisch/naturwissenschaften/MSc-Interdisciplinary-Sciences-Appendix.pdf",
      "programme": {
        "id": "eth-interdisciplinary-sciences-msc",
        "universityId": "eth-zurich-swiss-federal-institute-of-technology",
        "name": "MSc Interdisciplinary Sciences",
        "degreeType": "MSc",
        "faculty": "Natural Sciences and Mathematics | Interdisciplinary Sciences",
        "applicationUrl": "https://ethz.ch/en/studies/master/application.html",
        "sourceUrl": "https://ethz.ch/content/dam/ethz/common/docs/master-profile/englisch/naturwissenschaften/MSc-Interdisciplinary-Sciences-Appendix.pdf"
      },
      "windows": [
        {
          "intake": "Autumn 2026",
          "round": "International Bachelor's window",
          "applicantCategories": [
            "international-bachelors",
            "esop",
            "direct-doctorate"
          ],
          "opensAt": "2025-11-01",
          "opensAtBasis": "official",
          "closesAt": "2025-11-30"
        },
        {
          "intake": "Autumn 2026",
          "round": "Swiss Bachelor's window",
          "applicantCategories": [
            "swiss-bachelors"
          ],
          "opensAt": "2026-04-01",
          "opensAtBasis": "official",
          "closesAt": "2026-04-30"
        }
      ],
      "parseStatus": "parsed",
      "reviewReason": "Review the automatically discovered programme and application rounds.",
      "evidenceExcerpt": "ETH Zurich lists Interdisciplinary Sciences MSc in its official profiles of requirements. The official application dates page lists Autumn 2026 master's application windows: International Bachelor's window: 2025-11-01 to 2025-11-30; Swiss Bachelor's window: 2026-04-01 to 2026-04-30.",
      "reviewedBy": "codex",
      "reviewedAt": "2026-07-10T16:11:08.297399+00:00"
    },
    {
      "id": "new-programme:eth-landscape-architecture-msc",
      "type": "new-programme",
      "status": "approved",
      "universityId": "eth-zurich-swiss-federal-institute-of-technology",
      "detectedAt": "2026-07-08T06:36:09.250065+00:00",
      "sourceUrl": "https://ethz.ch/content/dam/ethz/common/docs/master-profile/englisch/arch-baug/MSc_LArch_Appendix.pdf",
      "programme": {
        "id": "eth-landscape-architecture-msc",
        "universityId": "eth-zurich-swiss-federal-institute-of-technology",
        "name": "MSc Landscape Architecture",
        "degreeType": "MSc",
        "faculty": "Architecture and Civil Engineering | Landscape Architecture",
        "applicationUrl": "https://ethz.ch/en/studies/master/application.html",
        "sourceUrl": "https://ethz.ch/content/dam/ethz/common/docs/master-profile/englisch/arch-baug/MSc_LArch_Appendix.pdf"
      },
      "windows": [
        {
          "intake": "Autumn 2026",
          "round": "International Bachelor's window",
          "applicantCategories": [
            "international-bachelors",
            "esop",
            "direct-doctorate"
          ],
          "opensAt": "2025-11-01",
          "opensAtBasis": "official",
          "closesAt": "2025-11-30"
        },
        {
          "intake": "Autumn 2026",
          "round": "Swiss Bachelor's window",
          "applicantCategories": [
            "swiss-bachelors"
          ],
          "opensAt": "2026-04-01",
          "opensAtBasis": "official",
          "closesAt": "2026-04-30"
        }
      ],
      "parseStatus": "parsed",
      "reviewReason": "Review the automatically discovered programme and application rounds.",
      "evidenceExcerpt": "ETH Zurich lists Landscape Architecture MSc in its official profiles of requirements. The official application dates page lists Autumn 2026 master's application windows: International Bachelor's window: 2025-11-01 to 2025-11-30; Swiss Bachelor's window: 2026-04-01 to 2026-04-30.",
      "reviewedBy": "codex",
      "reviewedAt": "2026-07-10T16:11:08.297399+00:00"
    },
    {
      "id": "new-programme:eth-management-technology-and-economics-msc",
      "type": "new-programme",
      "status": "approved",
      "universityId": "eth-zurich-swiss-federal-institute-of-technology",
      "detectedAt": "2026-07-08T06:36:09.250065+00:00",
      "sourceUrl": "https://ethz.ch/content/dam/ethz/common/docs/master-profile/englisch/management-sozialwissenschaften/MSc-MTEC-Appendix.pdf",
      "programme": {
        "id": "eth-management-technology-and-economics-msc",
        "universityId": "eth-zurich-swiss-federal-institute-of-technology",
        "name": "MSc Management, Technology, and Economics",
        "degreeType": "MSc",
        "faculty": "Management and Social Sciences | Management, Technology, and Economics",
        "applicationUrl": "https://ethz.ch/en/studies/master/application.html",
        "sourceUrl": "https://ethz.ch/content/dam/ethz/common/docs/master-profile/englisch/management-sozialwissenschaften/MSc-MTEC-Appendix.pdf"
      },
      "windows": [
        {
          "intake": "Autumn 2026",
          "round": "International Bachelor's window",
          "applicantCategories": [
            "international-bachelors",
            "esop",
            "direct-doctorate"
          ],
          "opensAt": "2025-11-01",
          "opensAtBasis": "official",
          "closesAt": "2025-11-30"
        },
        {
          "intake": "Autumn 2026",
          "round": "Swiss Bachelor's window",
          "applicantCategories": [
            "swiss-bachelors"
          ],
          "opensAt": "2026-04-01",
          "opensAtBasis": "official",
          "closesAt": "2026-04-30"
        }
      ],
      "parseStatus": "parsed",
      "reviewReason": "Review the automatically discovered programme and application rounds.",
      "evidenceExcerpt": "ETH Zurich lists Management, Technology, and Economics MSc in its official profiles of requirements. The official application dates page lists Autumn 2026 master's application windows: International Bachelor's window: 2025-11-01 to 2025-11-30; Swiss Bachelor's window: 2026-04-01 to 2026-04-30.",
      "reviewedBy": "codex",
      "reviewedAt": "2026-07-10T16:11:08.297399+00:00"
    },
    {
      "id": "new-programme:eth-materials-science-and-engineering-msc",
      "type": "new-programme",
      "status": "approved",
      "universityId": "eth-zurich-swiss-federal-institute-of-technology",
      "detectedAt": "2026-07-08T06:36:09.250065+00:00",
      "sourceUrl": "https://ethz.ch/content/dam/ethz/common/docs/master-profile/englisch/ingenieurwissenschaften/MSc_Materials%20Science%20and%20Engineering_Appendix.pdf",
      "programme": {
        "id": "eth-materials-science-and-engineering-msc",
        "universityId": "eth-zurich-swiss-federal-institute-of-technology",
        "name": "MSc Materials Science and Engineering",
        "degreeType": "MSc",
        "faculty": "Engineering Sciences | Materials Science and Engineering",
        "applicationUrl": "https://ethz.ch/en/studies/master/application.html",
        "sourceUrl": "https://ethz.ch/content/dam/ethz/common/docs/master-profile/englisch/ingenieurwissenschaften/MSc_Materials%20Science%20and%20Engineering_Appendix.pdf"
      },
      "windows": [
        {
          "intake": "Autumn 2026",
          "round": "International Bachelor's window",
          "applicantCategories": [
            "international-bachelors",
            "esop",
            "direct-doctorate"
          ],
          "opensAt": "2025-11-01",
          "opensAtBasis": "official",
          "closesAt": "2025-11-30"
        },
        {
          "intake": "Autumn 2026",
          "round": "Swiss Bachelor's window",
          "applicantCategories": [
            "swiss-bachelors"
          ],
          "opensAt": "2026-04-01",
          "opensAtBasis": "official",
          "closesAt": "2026-04-30"
        }
      ],
      "parseStatus": "parsed",
      "reviewReason": "Review the automatically discovered programme and application rounds.",
      "evidenceExcerpt": "ETH Zurich lists Materials Science and Engineering MSc in its official profiles of requirements. The official application dates page lists Autumn 2026 master's application windows: International Bachelor's window: 2025-11-01 to 2025-11-30; Swiss Bachelor's window: 2026-04-01 to 2026-04-30.",
      "reviewedBy": "codex",
      "reviewedAt": "2026-07-10T16:11:08.297399+00:00"
    },
    {
      "id": "new-programme:eth-mathematics-msc",
      "type": "new-programme",
      "status": "approved",
      "universityId": "eth-zurich-swiss-federal-institute-of-technology",
      "detectedAt": "2026-07-08T06:36:09.250065+00:00",
      "sourceUrl": "https://ethz.ch/content/dam/ethz/common/docs/master-profile/englisch/naturwissenschaften/MSc-Mathematics-Appendix.pdf",
      "programme": {
        "id": "eth-mathematics-msc",
        "universityId": "eth-zurich-swiss-federal-institute-of-technology",
        "name": "MSc Mathematics",
        "degreeType": "MSc",
        "faculty": "Natural Sciences and Mathematics | Mathematics",
        "applicationUrl": "https://ethz.ch/en/studies/master/application.html",
        "sourceUrl": "https://ethz.ch/content/dam/ethz/common/docs/master-profile/englisch/naturwissenschaften/MSc-Mathematics-Appendix.pdf"
      },
      "windows": [
        {
          "intake": "Autumn 2026",
          "round": "International Bachelor's window",
          "applicantCategories": [
            "international-bachelors",
            "esop",
            "direct-doctorate"
          ],
          "opensAt": "2025-11-01",
          "opensAtBasis": "official",
          "closesAt": "2025-11-30"
        },
        {
          "intake": "Autumn 2026",
          "round": "Swiss Bachelor's window",
          "applicantCategories": [
            "swiss-bachelors"
          ],
          "opensAt": "2026-04-01",
          "opensAtBasis": "official",
          "closesAt": "2026-04-30"
        }
      ],
      "parseStatus": "parsed",
      "reviewReason": "Review the automatically discovered programme and application rounds.",
      "evidenceExcerpt": "ETH Zurich lists Mathematics MSc in its official profiles of requirements. The official application dates page lists Autumn 2026 master's application windows: International Bachelor's window: 2025-11-01 to 2025-11-30; Swiss Bachelor's window: 2026-04-01 to 2026-04-30.",
      "reviewedBy": "codex",
      "reviewedAt": "2026-07-10T16:11:08.297399+00:00"
    },
    {
      "id": "new-programme:eth-mechanical-engineering-msc",
      "type": "new-programme",
      "status": "approved",
      "universityId": "eth-zurich-swiss-federal-institute-of-technology",
      "detectedAt": "2026-07-08T06:36:09.250065+00:00",
      "sourceUrl": "https://ethz.ch/content/dam/ethz/common/docs/master-profile/englisch/ingenieurwissenschaften/MSc-Mechanical-Engineering-Appendix.pdf",
      "programme": {
        "id": "eth-mechanical-engineering-msc",
        "universityId": "eth-zurich-swiss-federal-institute-of-technology",
        "name": "MSc Mechanical Engineering",
        "degreeType": "MSc",
        "faculty": "Engineering Sciences | Mechanical Engineering",
        "applicationUrl": "https://ethz.ch/en/studies/master/application.html",
        "sourceUrl": "https://ethz.ch/content/dam/ethz/common/docs/master-profile/englisch/ingenieurwissenschaften/MSc-Mechanical-Engineering-Appendix.pdf"
      },
      "windows": [
        {
          "intake": "Autumn 2026",
          "round": "International Bachelor's window",
          "applicantCategories": [
            "international-bachelors",
            "esop",
            "direct-doctorate"
          ],
          "opensAt": "2025-11-01",
          "opensAtBasis": "official",
          "closesAt": "2025-11-30"
        },
        {
          "intake": "Autumn 2026",
          "round": "Swiss Bachelor's window",
          "applicantCategories": [
            "swiss-bachelors"
          ],
          "opensAt": "2026-04-01",
          "opensAtBasis": "official",
          "closesAt": "2026-04-30"
        }
      ],
      "parseStatus": "parsed",
      "reviewReason": "Review the automatically discovered programme and application rounds.",
      "evidenceExcerpt": "ETH Zurich lists Mechanical Engineering MSc in its official profiles of requirements. The official application dates page lists Autumn 2026 master's application windows: International Bachelor's window: 2025-11-01 to 2025-11-30; Swiss Bachelor's window: 2026-04-01 to 2026-04-30.",
      "reviewedBy": "codex",
      "reviewedAt": "2026-07-10T16:11:08.297399+00:00"
    },
    {
      "id": "new-programme:eth-nuclear-engineering-msc",
      "type": "new-programme",
      "status": "approved",
      "universityId": "eth-zurich-swiss-federal-institute-of-technology",
      "detectedAt": "2026-07-08T06:36:09.250065+00:00",
      "sourceUrl": "https://ethz.ch/content/dam/ethz/common/docs/master-profile/englisch/ingenieurwissenschaften/MSc-Nuclear-Engineering-Appendix.pdf",
      "programme": {
        "id": "eth-nuclear-engineering-msc",
        "universityId": "eth-zurich-swiss-federal-institute-of-technology",
        "name": "MSc Nuclear Engineering",
        "degreeType": "MSc",
        "faculty": "Engineering Sciences | Nuclear Engineering",
        "applicationUrl": "https://ethz.ch/en/studies/master/application.html",
        "sourceUrl": "https://ethz.ch/content/dam/ethz/common/docs/master-profile/englisch/ingenieurwissenschaften/MSc-Nuclear-Engineering-Appendix.pdf"
      },
      "windows": [
        {
          "intake": "Autumn 2026",
          "round": "International Bachelor's window",
          "applicantCategories": [
            "international-bachelors",
            "esop",
            "direct-doctorate"
          ],
          "opensAt": "2025-11-01",
          "opensAtBasis": "official",
          "closesAt": "2025-11-30"
        },
        {
          "intake": "Autumn 2026",
          "round": "Swiss Bachelor's window",
          "applicantCategories": [
            "swiss-bachelors"
          ],
          "opensAt": "2026-04-01",
          "opensAtBasis": "official",
          "closesAt": "2026-04-30"
        }
      ],
      "parseStatus": "parsed",
      "reviewReason": "Review the automatically discovered programme and application rounds.",
      "evidenceExcerpt": "ETH Zurich lists Nuclear Engineering MSc in its official profiles of requirements. The official application dates page lists Autumn 2026 master's application windows: International Bachelor's window: 2025-11-01 to 2025-11-30; Swiss Bachelor's window: 2026-04-01 to 2026-04-30.",
      "reviewedBy": "codex",
      "reviewedAt": "2026-07-10T16:11:08.297399+00:00"
    },
    {
      "id": "new-programme:eth-pharmaceutical-sciences-msc",
      "type": "new-programme",
      "status": "approved",
      "universityId": "eth-zurich-swiss-federal-institute-of-technology",
      "detectedAt": "2026-07-08T06:36:09.250065+00:00",
      "sourceUrl": "https://ethz.ch/content/dam/ethz/common/docs/master-profile/englisch/naturwissenschaften/MSc-PharmSci-Appendix.pdf",
      "programme": {
        "id": "eth-pharmaceutical-sciences-msc",
        "universityId": "eth-zurich-swiss-federal-institute-of-technology",
        "name": "MSc Pharmaceutical Sciences",
        "degreeType": "MSc",
        "faculty": "Natural Sciences and Mathematics | Pharmaceutical Sciences",
        "applicationUrl": "https://ethz.ch/en/studies/master/application.html",
        "sourceUrl": "https://ethz.ch/content/dam/ethz/common/docs/master-profile/englisch/naturwissenschaften/MSc-PharmSci-Appendix.pdf"
      },
      "windows": [
        {
          "intake": "Autumn 2026",
          "round": "International Bachelor's window",
          "applicantCategories": [
            "international-bachelors",
            "esop",
            "direct-doctorate"
          ],
          "opensAt": "2025-11-01",
          "opensAtBasis": "official",
          "closesAt": "2025-11-30"
        },
        {
          "intake": "Autumn 2026",
          "round": "Swiss Bachelor's window",
          "applicantCategories": [
            "swiss-bachelors"
          ],
          "opensAt": "2026-04-01",
          "opensAtBasis": "official",
          "closesAt": "2026-04-30"
        }
      ],
      "parseStatus": "parsed",
      "reviewReason": "Review the automatically discovered programme and application rounds.",
      "evidenceExcerpt": "ETH Zurich lists Pharmaceutical Sciences MSc in its official profiles of requirements. The official application dates page lists Autumn 2026 master's application windows: International Bachelor's window: 2025-11-01 to 2025-11-30; Swiss Bachelor's window: 2026-04-01 to 2026-04-30.",
      "reviewedBy": "codex",
      "reviewedAt": "2026-07-10T16:11:08.297399+00:00"
    },
    {
      "id": "new-programme:eth-pharmacy-msc",
      "type": "new-programme",
      "status": "approved",
      "universityId": "eth-zurich-swiss-federal-institute-of-technology",
      "detectedAt": "2026-07-08T06:36:09.250065+00:00",
      "sourceUrl": "https://ethz.ch/content/dam/ethz/common/docs/master-profile/englisch/naturwissenschaften/MSc-Pharmacy-Appendix.pdf",
      "programme": {
        "id": "eth-pharmacy-msc",
        "universityId": "eth-zurich-swiss-federal-institute-of-technology",
        "name": "MSc Pharmacy",
        "degreeType": "MSc",
        "faculty": "Natural Sciences and Mathematics | Pharmacy",
        "applicationUrl": "https://ethz.ch/en/studies/master/application.html",
        "sourceUrl": "https://ethz.ch/content/dam/ethz/common/docs/master-profile/englisch/naturwissenschaften/MSc-Pharmacy-Appendix.pdf"
      },
      "windows": [
        {
          "intake": "Autumn 2026",
          "round": "International Bachelor's window",
          "applicantCategories": [
            "international-bachelors",
            "esop",
            "direct-doctorate"
          ],
          "opensAt": "2025-11-01",
          "opensAtBasis": "official",
          "closesAt": "2025-11-30"
        },
        {
          "intake": "Autumn 2026",
          "round": "Swiss Bachelor's window",
          "applicantCategories": [
            "swiss-bachelors"
          ],
          "opensAt": "2026-04-01",
          "opensAtBasis": "official",
          "closesAt": "2026-04-30"
        }
      ],
      "parseStatus": "parsed",
      "reviewReason": "Review the automatically discovered programme and application rounds.",
      "evidenceExcerpt": "ETH Zurich lists Pharmacy MSc in its official profiles of requirements. The official application dates page lists Autumn 2026 master's application windows: International Bachelor's window: 2025-11-01 to 2025-11-30; Swiss Bachelor's window: 2026-04-01 to 2026-04-30.",
      "reviewedBy": "codex",
      "reviewedAt": "2026-07-10T16:11:08.297399+00:00"
    },
    {
      "id": "new-programme:eth-physics-msc",
      "type": "new-programme",
      "status": "approved",
      "universityId": "eth-zurich-swiss-federal-institute-of-technology",
      "detectedAt": "2026-07-08T06:36:09.250065+00:00",
      "sourceUrl": "https://ethz.ch/content/dam/ethz/common/docs/master-profile/englisch/naturwissenschaften/MSc-Physics-Appendix.pdf",
      "programme": {
        "id": "eth-physics-msc",
        "universityId": "eth-zurich-swiss-federal-institute-of-technology",
        "name": "MSc Physics",
        "degreeType": "MSc",
        "faculty": "Natural Sciences and Mathematics | Physics",
        "applicationUrl": "https://ethz.ch/en/studies/master/application.html",
        "sourceUrl": "https://ethz.ch/content/dam/ethz/common/docs/master-profile/englisch/naturwissenschaften/MSc-Physics-Appendix.pdf"
      },
      "windows": [
        {
          "intake": "Autumn 2026",
          "round": "International Bachelor's window",
          "applicantCategories": [
            "international-bachelors",
            "esop",
            "direct-doctorate"
          ],
          "opensAt": "2025-11-01",
          "opensAtBasis": "official",
          "closesAt": "2025-11-30"
        },
        {
          "intake": "Autumn 2026",
          "round": "Swiss Bachelor's window",
          "applicantCategories": [
            "swiss-bachelors"
          ],
          "opensAt": "2026-04-01",
          "opensAtBasis": "official",
          "closesAt": "2026-04-30"
        }
      ],
      "parseStatus": "parsed",
      "reviewReason": "Review the automatically discovered programme and application rounds.",
      "evidenceExcerpt": "ETH Zurich lists Physics MSc in its official profiles of requirements. The official application dates page lists Autumn 2026 master's application windows: International Bachelor's window: 2025-11-01 to 2025-11-30; Swiss Bachelor's window: 2026-04-01 to 2026-04-30.",
      "reviewedBy": "codex",
      "reviewedAt": "2026-07-10T16:11:08.297399+00:00"
    },
    {
      "id": "new-programme:eth-process-engineering-msc",
      "type": "new-programme",
      "status": "approved",
      "universityId": "eth-zurich-swiss-federal-institute-of-technology",
      "detectedAt": "2026-07-08T06:36:09.250065+00:00",
      "sourceUrl": "https://ethz.ch/content/dam/ethz/common/docs/master-profile/englisch/ingenieurwissenschaften/MSc-Process-Engineering-Appendix.pdf",
      "programme": {
        "id": "eth-process-engineering-msc",
        "universityId": "eth-zurich-swiss-federal-institute-of-technology",
        "name": "MSc Process Engineering",
        "degreeType": "MSc",
        "faculty": "Engineering Sciences | Process Engineering",
        "applicationUrl": "https://ethz.ch/en/studies/master/application.html",
        "sourceUrl": "https://ethz.ch/content/dam/ethz/common/docs/master-profile/englisch/ingenieurwissenschaften/MSc-Process-Engineering-Appendix.pdf"
      },
      "windows": [
        {
          "intake": "Autumn 2026",
          "round": "International Bachelor's window",
          "applicantCategories": [
            "international-bachelors",
            "esop",
            "direct-doctorate"
          ],
          "opensAt": "2025-11-01",
          "opensAtBasis": "official",
          "closesAt": "2025-11-30"
        },
        {
          "intake": "Autumn 2026",
          "round": "Swiss Bachelor's window",
          "applicantCategories": [
            "swiss-bachelors"
          ],
          "opensAt": "2026-04-01",
          "opensAtBasis": "official",
          "closesAt": "2026-04-30"
        }
      ],
      "parseStatus": "parsed",
      "reviewReason": "Review the automatically discovered programme and application rounds.",
      "evidenceExcerpt": "ETH Zurich lists Process Engineering MSc in its official profiles of requirements. The official application dates page lists Autumn 2026 master's application windows: International Bachelor's window: 2025-11-01 to 2025-11-30; Swiss Bachelor's window: 2026-04-01 to 2026-04-30.",
      "reviewedBy": "codex",
      "reviewedAt": "2026-07-10T16:11:08.297399+00:00"
    },
    {
      "id": "new-programme:eth-quantum-engineering-msc",
      "type": "new-programme",
      "status": "approved",
      "universityId": "eth-zurich-swiss-federal-institute-of-technology",
      "detectedAt": "2026-07-08T06:36:09.250065+00:00",
      "sourceUrl": "https://ethz.ch/content/dam/ethz/common/docs/master-profile/englisch/ingenieurwissenschaften/MSc-QuantumEngineering-Appendix.pdf",
      "programme": {
        "id": "eth-quantum-engineering-msc",
        "universityId": "eth-zurich-swiss-federal-institute-of-technology",
        "name": "MSc Quantum Engineering",
        "degreeType": "MSc",
        "faculty": "Engineering Sciences | Natural Sciences and Mathematics | Quantum Engineering",
        "applicationUrl": "https://ethz.ch/en/studies/master/application.html",
        "sourceUrl": "https://ethz.ch/content/dam/ethz/common/docs/master-profile/englisch/ingenieurwissenschaften/MSc-QuantumEngineering-Appendix.pdf"
      },
      "windows": [
        {
          "intake": "Autumn 2026",
          "round": "International Bachelor's window",
          "applicantCategories": [
            "international-bachelors",
            "esop",
            "direct-doctorate"
          ],
          "opensAt": "2025-11-01",
          "opensAtBasis": "official",
          "closesAt": "2025-11-30"
        },
        {
          "intake": "Autumn 2026",
          "round": "Swiss Bachelor's window",
          "applicantCategories": [
            "swiss-bachelors"
          ],
          "opensAt": "2026-04-01",
          "opensAtBasis": "official",
          "closesAt": "2026-04-30"
        }
      ],
      "parseStatus": "parsed",
      "reviewReason": "Review the automatically discovered programme and application rounds.",
      "evidenceExcerpt": "ETH Zurich lists Quantum Engineering MSc in its official profiles of requirements. The official application dates page lists Autumn 2026 master's application windows: International Bachelor's window: 2025-11-01 to 2025-11-30; Swiss Bachelor's window: 2026-04-01 to 2026-04-30.",
      "reviewedBy": "codex",
      "reviewedAt": "2026-07-10T16:11:08.297399+00:00"
    },
    {
      "id": "new-programme:eth-science-technology-and-policy-msc",
      "type": "new-programme",
      "status": "approved",
      "universityId": "eth-zurich-swiss-federal-institute-of-technology",
      "detectedAt": "2026-07-08T06:36:09.250065+00:00",
      "sourceUrl": "https://ethz.ch/content/dam/ethz/common/docs/master-profile/englisch/management-sozialwissenschaften/STP-Appendix.pdf",
      "programme": {
        "id": "eth-science-technology-and-policy-msc",
        "universityId": "eth-zurich-swiss-federal-institute-of-technology",
        "name": "MSc Science, Technology and Policy",
        "degreeType": "MSc",
        "faculty": "Management and Social Sciences | Science, Technology and Policy",
        "applicationUrl": "https://ethz.ch/en/studies/master/application.html",
        "sourceUrl": "https://ethz.ch/content/dam/ethz/common/docs/master-profile/englisch/management-sozialwissenschaften/STP-Appendix.pdf"
      },
      "windows": [
        {
          "intake": "Autumn 2026",
          "round": "International Bachelor's window",
          "applicantCategories": [
            "international-bachelors",
            "esop",
            "direct-doctorate"
          ],
          "opensAt": "2025-11-01",
          "opensAtBasis": "official",
          "closesAt": "2025-11-30"
        },
        {
          "intake": "Autumn 2026",
          "round": "Swiss Bachelor's window",
          "applicantCategories": [
            "swiss-bachelors"
          ],
          "opensAt": "2026-04-01",
          "opensAtBasis": "official",
          "closesAt": "2026-04-30"
        }
      ],
      "parseStatus": "parsed",
      "reviewReason": "Review the automatically discovered programme and application rounds.",
      "evidenceExcerpt": "ETH Zurich lists Science, Technology and Policy MSc in its official profiles of requirements. The official application dates page lists Autumn 2026 master's application windows: International Bachelor's window: 2025-11-01 to 2025-11-30; Swiss Bachelor's window: 2026-04-01 to 2026-04-30.",
      "reviewedBy": "codex",
      "reviewedAt": "2026-07-10T16:11:08.297399+00:00"
    },
    {
      "id": "new-programme:eth-space-systems-msc",
      "type": "new-programme",
      "status": "approved",
      "universityId": "eth-zurich-swiss-federal-institute-of-technology",
      "detectedAt": "2026-07-08T06:36:09.250065+00:00",
      "sourceUrl": "https://ethz.ch/content/dam/ethz/common/docs/master-profile/englisch/systemorientierte-wissenschaften/MSc-SpaceSystems-Appendix.pdf",
      "programme": {
        "id": "eth-space-systems-msc",
        "universityId": "eth-zurich-swiss-federal-institute-of-technology",
        "name": "MSc Space Systems",
        "degreeType": "MSc",
        "faculty": "System-oriented Natural Sciences | Space Systems",
        "applicationUrl": "https://ethz.ch/en/studies/master/application.html",
        "sourceUrl": "https://ethz.ch/content/dam/ethz/common/docs/master-profile/englisch/systemorientierte-wissenschaften/MSc-SpaceSystems-Appendix.pdf"
      },
      "windows": [
        {
          "intake": "Autumn 2026",
          "round": "International Bachelor's window",
          "applicantCategories": [
            "international-bachelors",
            "esop",
            "direct-doctorate"
          ],
          "opensAt": "2025-11-01",
          "opensAtBasis": "official",
          "closesAt": "2025-11-30"
        },
        {
          "intake": "Autumn 2026",
          "round": "Swiss Bachelor's window",
          "applicantCategories": [
            "swiss-bachelors"
          ],
          "opensAt": "2026-04-01",
          "opensAtBasis": "official",
          "closesAt": "2026-04-30"
        }
      ],
      "parseStatus": "parsed",
      "reviewReason": "Review the automatically discovered programme and application rounds.",
      "evidenceExcerpt": "ETH Zurich lists Space Systems MSc in its official profiles of requirements. The official application dates page lists Autumn 2026 master's application windows: International Bachelor's window: 2025-11-01 to 2025-11-30; Swiss Bachelor's window: 2026-04-01 to 2026-04-30.",
      "reviewedBy": "codex",
      "reviewedAt": "2026-07-10T16:11:08.297399+00:00"
    },
    {
      "id": "new-programme:eth-spatial-development-and-infrastructure-systems-msc",
      "type": "new-programme",
      "status": "approved",
      "universityId": "eth-zurich-swiss-federal-institute-of-technology",
      "detectedAt": "2026-07-08T06:36:09.250065+00:00",
      "sourceUrl": "https://ethz.ch/content/dam/ethz/common/docs/master-profile/englisch/arch-baug/MSc-Spacial-Development-Appendix.pdf",
      "programme": {
        "id": "eth-spatial-development-and-infrastructure-systems-msc",
        "universityId": "eth-zurich-swiss-federal-institute-of-technology",
        "name": "MSc Spatial Development and Infrastructure Systems",
        "degreeType": "MSc",
        "faculty": "Architecture and Civil Engineering | Spatial Development and Infrastructure Systems",
        "applicationUrl": "https://ethz.ch/en/studies/master/application.html",
        "sourceUrl": "https://ethz.ch/content/dam/ethz/common/docs/master-profile/englisch/arch-baug/MSc-Spacial-Development-Appendix.pdf"
      },
      "windows": [
        {
          "intake": "Autumn 2026",
          "round": "International Bachelor's window",
          "applicantCategories": [
            "international-bachelors",
            "esop",
            "direct-doctorate"
          ],
          "opensAt": "2025-11-01",
          "opensAtBasis": "official",
          "closesAt": "2025-11-30"
        },
        {
          "intake": "Autumn 2026",
          "round": "Swiss Bachelor's window",
          "applicantCategories": [
            "swiss-bachelors"
          ],
          "opensAt": "2026-04-01",
          "opensAtBasis": "official",
          "closesAt": "2026-04-30"
        }
      ],
      "parseStatus": "parsed",
      "reviewReason": "Review the automatically discovered programme and application rounds.",
      "evidenceExcerpt": "ETH Zurich lists Spatial Development and Infrastructure Systems MSc in its official profiles of requirements. The official application dates page lists Autumn 2026 master's application windows: International Bachelor's window: 2025-11-01 to 2025-11-30; Swiss Bachelor's window: 2026-04-01 to 2026-04-30.",
      "reviewedBy": "codex",
      "reviewedAt": "2026-07-10T16:11:08.297399+00:00"
    }
  ]
}
